[[{"transfer_0.2": {"AUC ROC": 0.725413, "AUC PR": 0.029836, "CLL": -0.333404, "Precision": [0.072802, 0.5], "Recall": 0.203846, "F1": 0.107287, "Learning time": 23.45486407852173, "parameter": {"AUC ROC": 0.56107, "AUC PR": 0.001604, "CLL": -0.378648, "Precision": [NaN, 0.5], "Recall": 0.0, "F1": NaN, "Learning time": 1.692}, "Mapping time": 0.09571695327758789}, "transfer_0.4": {"AUC ROC": 0.703329, "AUC PR": 0.099649, "CLL": -0.330897, "Precision": [0.241176, 0.5], "Recall": 0.157692, "F1": 0.190698, "Learning time": 36.859738998413086, "parameter": {"AUC ROC": 0.557957, "AUC PR": 0.001588, "CLL": -0.366229, "Precision": [NaN, 0.5], "Recall": 0.0, "F1": NaN, "Learning time": 2.341}, "Mapping time": 0.09571695327758789}, "transfer_0.6": {"AUC ROC": 0.693909, "AUC PR": 0.099519, "CLL": -0.341007, "Precision": [0.34375, 0.5], "Recall": 0.126923, "F1": 0.185393, "Learning time": 68.4839614238739, "parameter": {"AUC ROC": 0.558527, "AUC PR": 0.001596, "CLL": -0.37009, "Precision": [NaN, 0.5], "Recall": 0.0, "F1": NaN, "Learning time": 3.021}, "Mapping time": 0.09571695327758789}, "transfer_0.8": {"AUC ROC": 0.755045, "AUC PR": 0.075983, "CLL": -0.322895, "Precision": [0.064322, 0.5], "Recall": 0.246154, "F1": 0.101992, "Learning time": 68.60020296096802, "parameter": {"AUC ROC": 0.55993, "AUC PR": 0.0016, "CLL": -0.372333, "Precision": [NaN, 0.5], "Recall": 0.0, "F1": NaN, "Learning time": 3.717}, "Mapping time": 0.09571695327758789}, "transfer_1.0": {"AUC ROC": 0.790673, "AUC PR": 0.119184, "CLL": -0.309892, "Precision": [0.117073, 0.5], "Recall": 0.276923, "F1": 0.164571, "Learning time": 125.53184734725951, "parameter": {"AUC ROC": 0.552732, "AUC PR": 0.001569, "CLL": -0.366808, "Precision": [NaN, 0.5], "Recall": 0.0, "F1": NaN, "Learning time": 4.42}, "Mapping time": 0.09571695327758789}}, {"transfer_0.2": {"AUC ROC": 0.71402, "AUC PR": 0.060885, "CLL": -0.3039, "Precision": [0.036232, 0.5], "Recall": 0.192308, "F1": 0.060976, "Learning time": 24.263004770278933, "parameter": {"AUC ROC": 0.565123, "AUC PR": 0.001652, "CLL": -0.361704, "Precision": [NaN, 0.5], "Recall": 0.0, "F1": NaN, "Learning time": 1.795}, "Mapping time": 0.09571695327758789}, "transfer_0.4": {"AUC ROC": 0.77737, "AUC PR": 0.078828, "CLL": -0.290588, "Precision": [0.066593, 0.5], "Recall": 0.230769, "F1": 0.103359, "Learning time": 59.673462919235234, "parameter": {"AUC ROC": 0.564397, "AUC PR": 0.001699, "CLL": -0.375161, "Precision": [NaN, 0.5], "Recall": 0.0, "F1": NaN, "Learning time": 2.515}, "Mapping time": 0.09571695327758789}, "transfer_0.6": {"AUC ROC": 0.743363, "AUC PR": 0.069896, "CLL": -0.312553, "Precision": [0.066882, 0.5], "Recall": 0.238462, "F1": 0.104465, "Learning time": 57.52536680221557, "parameter": {"AUC ROC": 0.558896, "AUC PR": 0.001609, "CLL": -0.361124, "Precision": [NaN, 0.5], "Recall": 0.0, "F1": NaN, "Learning time": 3.005}, "Mapping time": 0.09571695327758789}, "transfer_0.8": {"AUC ROC": 0.733236, "AUC PR": 0.061522, "CLL": -0.324368, "Precision": [0.213235, 0.5], "Recall": 0.111538, "F1": 0.146465, "Learning time": 113.46326264572144, "parameter": {"AUC ROC": 0.546996, "AUC PR": 0.001517, "CLL": -0.37325, "Precision": [NaN, 0.5], "Recall": 0.0, "F1": NaN, "Learning time": 3.851}, "Mapping time": 0.09571695327758789}, "transfer_1.0": {"AUC ROC": 0.678851, "AUC PR": 0.055172, "CLL": -0.337627, "Precision": [0.339623, 0.5], "Recall": 0.069231, "F1": 0.115016, "Learning time": 147.8086325416565, "parameter": {"AUC ROC": 0.554627, "AUC PR": 0.001576, "CLL": -0.368893, "Precision": [NaN, 0.5], "Recall": 0.0, "F1": NaN, "Learning time": 4.482}, "Mapping time": 0.09571695327758789}}, {"transfer_0.2": {"AUC ROC": 0.653478, "AUC PR": 0.009302, "CLL": -0.343045, "Precision": [0.008391, 0.5], "Recall": 0.085271, "F1": 0.015278, "Learning time": 27.98720372390747, "parameter": {"AUC ROC": 0.553165, "AUC PR": 0.001526, "CLL": -0.375908, "Precision": [0.0, 0.5], "Recall": 0.0, "F1": NaN, "Learning time": 1.746}, "Mapping time": 0.09571695327758789}, "transfer_0.4": {"AUC ROC": 0.72921, "AUC PR": 0.053147, "CLL": -0.325704, "Precision": [0.067019, 0.5], "Recall": 0.147287, "F1": 0.092121, "Learning time": 45.691815004348754, "parameter": {"AUC ROC": 0.558112, "AUC PR": 0.001557, "CLL": -0.356858, "Precision": [NaN, 0.5], "Recall": 0.0, "F1": NaN, "Learning time": 2.346}, "Mapping time": 0.09571695327758789}, "transfer_0.6": {"AUC ROC": 0.754251, "AUC PR": 0.097202, "CLL": -0.325946, "Precision": [0.262626, 0.5], "Recall": 0.100775, "F1": 0.145658, "Learning time": 56.60611137771606, "parameter": {"AUC ROC": 0.555945, "AUC PR": 0.001542, "CLL": -0.365402, "Precision": [NaN, 0.5], "Recall": 0.0, "F1": NaN, "Learning time": 3.003}, "Mapping time": 0.09571695327758789}, "transfer_0.8": {"AUC ROC": 0.797769, "AUC PR": 0.131903, "CLL": -0.315322, "Precision": [0.123003, 0.5], "Recall": 0.29845, "F1": 0.174208, "Learning time": 68.87730347633362, "parameter": {"AUC ROC": 0.556182, "AUC PR": 0.001551, "CLL": -0.370483, "Precision": [NaN, 0.5], "Recall": 0.0, "F1": NaN, "Learning time": 3.53}, "Mapping time": 0.09571695327758789}, "transfer_1.0": {"AUC ROC": 0.779253, "AUC PR": 0.10588, "CLL": -0.320366, "Precision": [0.126623, 0.5], "Recall": 0.151163, "F1": 0.137809, "Learning time": 121.84089492988586, "parameter": {"AUC ROC": 0.555945, "AUC PR": 0.001542, "CLL": -0.36952, "Precision": [NaN, 0.5], "Recall": 0.0, "F1": NaN, "Learning time": 4.193}, "Mapping time": 0.09571695327758789}}], [{"transfer_0.2": {"AUC ROC": 0.55139, "AUC PR": 0.001573, "CLL": -0.36198, "Precision": [NaN, 0.5], "Recall": 0.0, "F1": NaN, "Learning time": 19.690876264572143, "parameter": {"AUC ROC": 0.55139, "AUC PR": 0.001573, "CLL": -0.36198, "Precision": [NaN, 0.5], "Recall": 0.0, "F1": NaN, "Learning time": 1.738}, "Mapping time": 0.06141185760498047}, "transfer_0.4": {"AUC ROC": 0.772307, "AUC PR": 0.077549, "CLL": -0.325405, "Precision": [0.06747, 0.5], "Recall": 0.107692, "F1": 0.082963, "Learning time": 43.38559242248535, "parameter": {"AUC ROC": 0.553384, "AUC PR": 0.001584, "CLL": -0.364064, "Precision": [NaN, 0.5], "Recall": 0.0, "F1": NaN, "Learning time": 2.46}, "Mapping time": 0.06141185760498047}, "transfer_0.6": {"AUC ROC": 0.735281, "AUC PR": 0.060111, "CLL": -0.333059, "Precision": [0.025806, 0.5], "Recall": 0.092308, "F1": 0.040336, "Learning time": 56.96655884552002, "parameter": {"AUC ROC": 0.560916, "AUC PR": 0.001607, "CLL": -0.369851, "Precision": [NaN, 0.5], "Recall": 0.0, "F1": NaN, "Learning time": 2.979}, "Mapping time": 0.06141185760498047}, "transfer_0.8": {"AUC ROC": 0.69711, "AUC PR": 0.082458, "CLL": -0.340704, "Precision": [0.444444, 0.5], "Recall": 0.107692, "F1": 0.173375, "Learning time": 86.05723767852783, "parameter": {"AUC ROC": 0.560954, "AUC PR": 0.001608, "CLL": -0.369597, "Precision": [NaN, 0.5], "Recall": 0.0, "F1": NaN, "Learning time": 3.645}, "Mapping time": 0.06141185760498047}, "transfer_1.0": {"AUC ROC": 0.702774, "AUC PR": 0.100628, "CLL": -0.338181, "Precision": [0.43662, 0.5], "Recall": 0.119231, "F1": 0.187311, "Learning time": 90.71827880287171, "parameter": {"AUC ROC": 0.560363, "AUC PR": 0.001605, "CLL": -0.372214, "Precision": [NaN, 0.5], "Recall": 0.0, "F1": NaN, "Learning time": 4.199}, "Mapping time": 0.06141185760498047}}, {"transfer_0.2": {"AUC ROC": 0.720733, "AUC PR": 0.031904, "CLL": -0.322153, "Precision": [0.037594, 0.5], "Recall": 0.096154, "F1": 0.054054, "Learning time": 23.193478605270386, "parameter": {"AUC ROC": 0.565114, "AUC PR": 0.001652, "CLL": -0.366913, "Precision": [NaN, 0.5], "Recall": 0.0, "F1": NaN, "Learning time": 1.711}, "Mapping time": 0.06141185760498047}, "transfer_0.4": {"AUC ROC": 0.736354, "AUC PR": 0.090673, "CLL": -0.325178, "Precision": [0.185, 0.5], "Recall": 0.142308, "F1": 0.16087, "Learning time": 36.74673920440674, "parameter": {"AUC ROC": 0.558801, "AUC PR": 0.001603, "CLL": -0.363519, "Precision": [NaN, 0.5], "Recall": 0.0, "F1": NaN, "Learning time": 2.541}, "Mapping time": 0.06141185760498047}, "transfer_0.6": {"AUC ROC": 0.727755, "AUC PR": 0.089496, "CLL": -0.311817, "Precision": [0.071521, 0.5], "Recall": 0.211538, "F1": 0.1069, "Learning time": 53.5200475692749, "parameter": {"AUC ROC": 0.554218, "AUC PR": 0.001548, "CLL": -0.362214, "Precision": [NaN, 0.5], "Recall": 0.0, "F1": NaN, "Learning time": 3.023}, "Mapping time": 0.06141185760498047}, "transfer_0.8": {"AUC ROC": 0.646184, "AUC PR": 0.056526, "CLL": -0.337008, "Precision": [0.391304, 0.5], "Recall": 0.103846, "F1": 0.164134, "Learning time": 62.851210662841794, "parameter": {"AUC ROC": 0.546977, "AUC PR": 0.001513, "CLL": -0.368444, "Precision": [NaN, 0.5], "Recall": 0.0, "F1": NaN, "Learning time": 3.527}, "Mapping time": 0.06141185760498047}, "transfer_1.0": {"AUC ROC": 0.636216, "AUC PR": 0.032728, "CLL": -0.35444, "Precision": [0.352941, 0.5], "Recall": 0.046154, "F1": 0.081633, "Learning time": 79.23841043472291, "parameter": {"AUC ROC": 0.557112, "AUC PR": 0.001599, "CLL": -0.366167, "Precision": [NaN, 0.5], "Recall": 0.0, "F1": NaN, "Learning time": 4.355}, "Mapping time": 0.06141185760498047}}, {"transfer_0.2": {"AUC ROC": 0.777615, "AUC PR": 0.053259, "CLL": -0.310776, "Precision": [0.088575, 0.5], "Recall": 0.267442, "F1": 0.133076, "Learning time": 25.20225022506714, "parameter": {"AUC ROC": 0.555356, "AUC PR": 0.001537, "CLL": -0.368549, "Precision": [NaN, 0.5], "Recall": 0.0, "F1": NaN, "Learning time": 1.942}, "Mapping time": 0.06141185760498047}, "transfer_0.4": {"AUC ROC": 0.762236, "AUC PR": 0.101022, "CLL": -0.319817, "Precision": [0.10757, 0.5], "Recall": 0.209302, "F1": 0.142105, "Learning time": 43.887083002090456, "parameter": {"AUC ROC": 0.55531, "AUC PR": 0.001537, "CLL": -0.366555, "Precision": [NaN, 0.5], "Recall": 0.0, "F1": NaN, "Learning time": 2.493}, "Mapping time": 0.06141185760498047}, "transfer_0.6": {"AUC ROC": 0.63429, "AUC PR": 0.063165, "CLL": -0.339842, "Precision": [0.410959, 0.5], "Recall": 0.116279, "F1": 0.181269, "Learning time": 64.62611200714112, "parameter": {"AUC ROC": 0.565476, "AUC PR": 0.001622, "CLL": -0.37629, "Precision": [NaN, 0.5], "Recall": 0.0, "F1": NaN, "Learning time": 3.012}, "Mapping time": 0.06141185760498047}, "transfer_0.8": {"AUC ROC": 0.715472, "AUC PR": 0.077647, "CLL": -0.332947, "Precision": [0.161716, 0.5], "Recall": 0.189922, "F1": 0.174688, "Learning time": 84.32894995117188, "parameter": {"AUC ROC": 0.557177, "AUC PR": 0.00155, "CLL": -0.363301, "Precision": [NaN, 0.5], "Recall": 0.0, "F1": NaN, "Learning time": 3.693}, "Mapping time": 0.06141185760498047}, "transfer_1.0": {"AUC ROC": 0.797464, "AUC PR": 0.113973, "CLL": -0.31579, "Precision": [0.09215, 0.5], "Recall": 0.313953, "F1": 0.14248, "Learning time": 102.83861062812805, "parameter": {"AUC ROC": 0.558189, "AUC PR": 0.001556, "CLL": -0.363833, "Precision": [NaN, 0.5], "Recall": 0.0, "F1": NaN, "Learning time": 4.301}, "Mapping time": 0.06141185760498047}}], [{"transfer_0.2": {"AUC ROC": 0.707278, "AUC PR": 0.098429, "CLL": -0.341994, "Precision": [0.116041, 0.5], "Recall": 0.130769, "F1": 0.122966, "Learning time": 21.933983573913572, "parameter": {"AUC ROC": 0.568613, "AUC PR": 0.001666, "CLL": -0.377672, "Precision": [NaN, 0.5], "Recall": 0.0, "F1": NaN, "Learning time": 1.767}, "Mapping time": 0.06266617774963379}, "transfer_0.4": {"AUC ROC": 0.790739, "AUC PR": 0.080303, "CLL": -0.317928, "Precision": [0.069746, 0.5], "Recall": 0.284615, "F1": 0.112036, "Learning time": 55.71125650596619, "parameter": {"AUC ROC": 0.55139, "AUC PR": 0.001574, "CLL": -0.364871, "Precision": [NaN, 0.5], "Recall": 0.0, "F1": NaN, "Learning time": 2.406}, "Mapping time": 0.06266617774963379}, "transfer_0.6": {"AUC ROC": 0.736398, "AUC PR": 0.089358, "CLL": -0.32792, "Precision": [0.151625, 0.5], "Recall": 0.161538, "F1": 0.156425, "Learning time": 52.47367632102966, "parameter": {"AUC ROC": 0.557991, "AUC PR": 0.001589, "CLL": -0.372772, "Precision": [NaN, 0.5], "Recall": 0.0, "F1": NaN, "Learning time": 2.996}, "Mapping time": 0.06266617774963379}, "transfer_0.8": {"AUC ROC": 0.753888, "AUC PR": 0.074826, "CLL": -0.314812, "Precision": [0.081568, 0.5], "Recall": 0.296154, "F1": 0.127907, "Learning time": 84.45700255393982, "parameter": {"AUC ROC": 0.557957, "AUC PR": 0.001588, "CLL": -0.363912, "Precision": [NaN, 0.5], "Recall": 0.0, "F1": NaN, "Learning time": 3.634}, "Mapping time": 0.06266617774963379}, "transfer_1.0": {"AUC ROC": 0.744856, "AUC PR": 0.117304, "CLL": -0.338083, "Precision": [0.353659, 0.5], "Recall": 0.111538, "F1": 0.169591, "Learning time": 162.07016582870483, "parameter": {"AUC ROC": 0.552649, "AUC PR": 0.001567, "CLL": -0.359421, "Precision": [NaN, 0.5], "Recall": 0.0, "F1": NaN, "Learning time": 4.259}, "Mapping time": 0.06266617774963379}}, {"transfer_0.2": {"AUC ROC": 0.726483, "AUC PR": 0.045344, "CLL": -0.319886, "Precision": [0.070652, 0.5], "Recall": 0.1, "F1": 0.082803, "Learning time": 22.00003265953064, "parameter": {"AUC ROC": 0.559903, "AUC PR": 0.001585, "CLL": -0.368331, "Precision": [NaN, 0.5], "Recall": 0.0, "F1": NaN, "Learning time": 1.858}, "Mapping time": 0.06266617774963379}, "transfer_0.4": {"AUC ROC": 0.729009, "AUC PR": 0.062626, "CLL": -0.332706, "Precision": [0.287879, 0.5], "Recall": 0.073077, "F1": 0.116564, "Learning time": 35.54546709823609, "parameter": {"AUC ROC": 0.554627, "AUC PR": 0.001576, "CLL": -0.366499, "Precision": [NaN, 0.5], "Recall": 0.0, "F1": NaN, "Learning time": 2.463}, "Mapping time": 0.06266617774963379}, "transfer_0.6": {"AUC ROC": 0.731941, "AUC PR": 0.071965, "CLL": -0.311282, "Precision": [0.074526, 0.5], "Recall": 0.211538, "F1": 0.11022, "Learning time": 56.579160066604615, "parameter": {"AUC ROC": 0.546977, "AUC PR": 0.001513, "CLL": -0.366801, "Precision": [NaN, 0.5], "Recall": 0.0, "F1": NaN, "Learning time": 3.153}, "Mapping time": 0.06266617774963379}, "transfer_0.8": {"AUC ROC": 0.733477, "AUC PR": 0.08157, "CLL": -0.307432, "Precision": [0.071078, 0.5], "Recall": 0.223077, "F1": 0.107807, "Learning time": 80.93313354110718, "parameter": {"AUC ROC": 0.554218, "AUC PR": 0.001548, "CLL": -0.36425, "Precision": [NaN, 0.5], "Recall": 0.0, "F1": NaN, "Learning time": 3.599}, "Mapping time": 0.06266617774963379}, "transfer_1.0": {"AUC ROC": 0.754157, "AUC PR": 0.071405, "CLL": -0.323479, "Precision": [0.217391, 0.5], "Recall": 0.115385, "F1": 0.150754, "Learning time": 82.66094863700866, "parameter": {"AUC ROC": 0.557276, "AUC PR": 0.0016, "CLL": -0.371589, "Precision": [0.0, 0.5], "Recall": 0.0, "F1": NaN, "Learning time": 4.248}, "Mapping time": 0.06266617774963379}}, {"transfer_0.2": {"AUC ROC": 0.666591, "AUC PR": 0.035465, "CLL": -0.337503, "Precision": [0.118012, 0.5], "Recall": 0.147287, "F1": 0.131034, "Learning time": 42.5704358921051, "parameter": {"AUC ROC": 0.562699, "AUC PR": 0.001591, "CLL": -0.356089, "Precision": [NaN, 0.5], "Recall": 0.0, "F1": NaN, "Learning time": 1.904}, "Mapping time": 0.06266617774963379}, "transfer_0.4": {"AUC ROC": 0.688257, "AUC PR": 0.053248, "CLL": -0.331076, "Precision": [0.096386, 0.5], "Recall": 0.124031, "F1": 0.108475, "Learning time": 44.5809433555603, "parameter": {"AUC ROC": 0.556394, "AUC PR": 0.001565, "CLL": -0.362413, "Precision": [NaN, 0.5], "Recall": 0.0, "F1": NaN, "Learning time": 2.372}, "Mapping time": 0.06266617774963379}, "transfer_0.6": {"AUC ROC": 0.789874, "AUC PR": 0.119587, "CLL": -0.322547, "Precision": [0.272727, 0.5], "Recall": 0.139535, "F1": 0.184615, "Learning time": 68.67650624847411, "parameter": {"AUC ROC": 0.556501, "AUC PR": 0.00157, "CLL": -0.374763, "Precision": [NaN, 0.5], "Recall": 0.0, "F1": NaN, "Learning time": 3.046}, "Mapping time": 0.06266617774963379}, "transfer_0.8": {"AUC ROC": 0.772255, "AUC PR": 0.096957, "CLL": -0.317583, "Precision": [0.079646, 0.5], "Recall": 0.27907, "F1": 0.123924, "Learning time": 91.52954638671875, "parameter": {"AUC ROC": 0.556394, "AUC PR": 0.001565, "CLL": -0.363715, "Precision": [NaN, 0.5], "Recall": 0.0, "F1": NaN, "Learning time": 3.731}, "Mapping time": 0.06266617774963379}, "transfer_1.0": {"AUC ROC": 0.699094, "AUC PR": 0.059734, "CLL": -0.337639, "Precision": [0.047288, 0.5], "Recall": 0.131783, "F1": 0.069601, "Learning time": 76.27060580062866, "parameter": {"AUC ROC": 0.555945, "AUC PR": 0.001542, "CLL": -0.364489, "Precision": [NaN, 0.5], "Recall": 0.0, "F1": NaN, "Learning time": 4.395}, "Mapping time": 0.06266617774963379}}]]