{"fasttext": {"euclidean": [{"TP": [33, 20, 9, 32, 16], "FP": [207, 50, 7, 193, 37], "TN": [1607, 291, 84, 1295, 308], "FN": [2, 0, 0, 1, 0]}, {"TP": [33, 20, 9, 32, 16], "FP": [207, 50, 7, 193, 37], "TN": [1607, 291, 84, 1295, 308], "FN": [2, 0, 0, 1, 0]}, {"TP": [33, 20, 9, 32, 16], "FP": [207, 50, 7, 193, 37], "TN": [1607, 291, 84, 1295, 308], "FN": [2, 0, 0, 1, 0]}, {"TP": [33, 20, 9, 32, 16], "FP": [207, 50, 7, 193, 37], "TN": [1607, 291, 84, 1295, 308], "FN": [2, 0, 0, 1, 0]}, {"TP": [33, 20, 9, 32, 16], "FP": [207, 50, 7, 193, 37], "TN": [1607, 291, 84, 1295, 308], "FN": [2, 0, 0, 1, 0]}], "softcosine": [{"TP": [34, 20, 9, 31, 16], "FP": [225, 28, 7, 192, 48], "TN": [1589, 313, 84, 1296, 297], "FN": [1, 0, 0, 2, 0]}, {"TP": [34, 20, 9, 31, 16], "FP": [225, 28, 7, 192, 48], "TN": [1589, 313, 84, 1296, 297], "FN": [1, 0, 0, 2, 0]}, {"TP": [34, 20, 9, 31, 16], "FP": [225, 28, 7, 192, 48], "TN": [1589, 313, 84, 1296, 297], "FN": [1, 0, 0, 2, 0]}, {"TP": [34, 20, 9, 31, 16], "FP": [225, 28, 7, 192, 48], "TN": [1589, 313, 84, 1296, 297], "FN": [1, 0, 0, 2, 0]}, {"TP": [34, 20, 9, 31, 16], "FP": [225, 28, 7, 192, 48], "TN": [1589, 313, 84, 1296, 297], "FN": [1, 0, 0, 2, 0]}], "wmd": [{"TP": [31, 19, 9, 33, 15], "FP": [152, 21, 7, 229, 46], "TN": [1662, 320, 84, 1259, 299], "FN": [4, 1, 0, 0, 1]}, {"TP": [31, 19, 9, 33, 15], "FP": [152, 21, 7, 229, 46], "TN": [1662, 320, 84, 1259, 299], "FN": [4, 1, 0, 0, 1]}, {"TP": [31, 19, 9, 33, 15], "FP": [152, 21, 7, 229, 46], "TN": [1662, 320, 84, 1259, 299], "FN": [4, 1, 0, 0, 1]}, {"TP": [31, 19, 9, 33, 15], "FP": [152, 21, 7, 229, 46], "TN": [1662, 320, 84, 1259, 299], "FN": [4, 1, 0, 0, 1]}, {"TP": [31, 19, 9, 33, 15], "FP": [152, 21, 7, 229, 46], "TN": [1662, 320, 84, 1259, 299], "FN": [4, 1, 0, 0, 1]}], "relax-wmd": [{"TP": [33, 19, 9, 31, 16], "FP": [217, 20, 6, 182, 40], "TN": [1597, 321, 85, 1306, 305], "FN": [2, 1, 0, 2, 0]}, {"TP": [33, 19, 9, 31, 16], "FP": [217, 20, 6, 182, 40], "TN": [1597, 321, 85, 1306, 305], "FN": [2, 1, 0, 2, 0]}, {"TP": [33, 19, 9, 31, 16], "FP": [217, 20, 6, 182, 40], "TN": [1597, 321, 85, 1306, 305], "FN": [2, 1, 0, 2, 0]}, {"TP": [33, 19, 9, 31, 16], "FP": [217, 20, 6, 182, 40], "TN": [1597, 321, 85, 1306, 305], "FN": [2, 1, 0, 2, 0]}, {"TP": [33, 19, 9, 31, 16], "FP": [217, 20, 6, 182, 40], "TN": [1597, 321, 85, 1306, 305], "FN": [2, 1, 0, 2, 0]}]}}