[[{"transfer_0.2": {"AUC ROC": 1.0, "AUC PR": 1.0, "CLL": -0.063421, "Precision": [1.0, 0.5], "Recall": 1.0, "F1": 1.0, "Learning time": 4.00464135169983, "parameter": {"AUC ROC": 0.5, "AUC PR": 0.016647, "CLL": -0.386604, "Precision": [NaN, 0.5], "Recall": 0.0, "F1": NaN}, "Mapping time": 0.015455961227416992}, "transfer_0.4": {"AUC ROC": 1.0, "AUC PR": 1.0, "CLL": -0.063421, "Precision": [1.0, 0.5], "Recall": 1.0, "F1": 1.0, "Learning time": 4.729698301315308, "parameter": {"AUC ROC": 0.5, "AUC PR": 0.016647, "CLL": -0.386892, "Precision": [NaN, 0.5], "Recall": 0.0, "F1": NaN}, "Mapping time": 0.015455961227416992}, "transfer_0.6": {"AUC ROC": 1.0, "AUC PR": 1.0, "CLL": -0.063421, "Precision": [1.0, 0.5], "Recall": 1.0, "F1": 1.0, "Learning time": 5.72818126296997, "parameter": {"AUC ROC": 0.5, "AUC PR": 0.016647, "CLL": -0.382022, "Precision": [NaN, 0.5], "Recall": 0.0, "F1": NaN}, "Mapping time": 0.015455961227416992}, "transfer_0.8": {"AUC ROC": 1.0, "AUC PR": 1.0, "CLL": -0.063436, "Precision": [1.0, 0.5], "Recall": 1.0, "F1": 1.0, "Learning time": 6.326534568786621, "parameter": {"AUC ROC": 0.5, "AUC PR": 0.016647, "CLL": -0.384203, "Precision": [NaN, 0.5], "Recall": 0.0, "F1": NaN}, "Mapping time": 0.015455961227416992}, "transfer_1.0": {"AUC ROC": 1.0, "AUC PR": 1.0, "CLL": -0.063421, "Precision": [1.0, 0.5], "Recall": 1.0, "F1": 1.0, "Learning time": 7.0341389350891115, "parameter": {"AUC ROC": 0.5, "AUC PR": 0.016647, "CLL": -0.389185, "Precision": [NaN, 0.5], "Recall": 0.0, "F1": NaN}, "Mapping time": 0.015455961227416992}}, {"transfer_0.2": {"AUC ROC": 1.0, "AUC PR": 1.0, "CLL": -0.063422, "Precision": [1.0, 0.5], "Recall": 1.0, "F1": 1.0, "Learning time": 3.9062306900024413, "parameter": {"AUC ROC": 0.5, "AUC PR": 0.016662, "CLL": -0.395476, "Precision": [NaN, 0.5], "Recall": 0.0, "F1": NaN}, "Mapping time": 0.015455961227416992}, "transfer_0.4": {"AUC ROC": 1.0, "AUC PR": 1.0, "CLL": -0.063003, "Precision": [1.0, 0.5], "Recall": 1.0, "F1": 1.0, "Learning time": 4.6973995609283445, "parameter": {"AUC ROC": 0.5, "AUC PR": 0.016662, "CLL": -0.386651, "Precision": [NaN, 0.5], "Recall": 0.0, "F1": NaN}, "Mapping time": 0.015455961227416992}, "transfer_0.6": {"AUC ROC": 1.0, "AUC PR": 1.0, "CLL": -0.063422, "Precision": [1.0, 0.5], "Recall": 1.0, "F1": 1.0, "Learning time": 5.711888204574585, "parameter": {"AUC ROC": 0.5, "AUC PR": 0.016662, "CLL": -0.384448, "Precision": [NaN, 0.5], "Recall": 0.0, "F1": NaN}, "Mapping time": 0.015455961227416992}, "transfer_0.8": {"AUC ROC": 1.0, "AUC PR": 1.0, "CLL": -0.063422, "Precision": [1.0, 0.5], "Recall": 1.0, "F1": 1.0, "Learning time": 6.495193052291871, "parameter": {"AUC ROC": 0.5, "AUC PR": 0.016662, "CLL": -0.375052, "Precision": [NaN, 0.5], "Recall": 0.0, "F1": NaN}, "Mapping time": 0.015455961227416992}, "transfer_1.0": {"AUC ROC": 1.0, "AUC PR": 1.0, "CLL": -0.063422, "Precision": [1.0, 0.5], "Recall": 1.0, "F1": 1.0, "Learning time": 7.382883039474487, "parameter": {"AUC ROC": 0.5, "AUC PR": 0.016662, "CLL": -0.377848, "Precision": [NaN, 0.5], "Recall": 0.0, "F1": NaN}, "Mapping time": 0.015455961227416992}}, {"transfer_0.2": {"AUC ROC": 1.0, "AUC PR": 1.0, "CLL": -0.120612, "Precision": [0.626761, 0.5], "Recall": 1.0, "F1": 0.770563, "Learning time": 3.642340000152588, "parameter": {"AUC ROC": 0.5, "AUC PR": 0.047837, "CLL": -0.418738, "Precision": [NaN, 0.5], "Recall": 0.0, "F1": NaN}, "Mapping time": 0.015455961227416992}, "transfer_0.4": {"AUC ROC": 1.0, "AUC PR": 1.0, "CLL": -0.074017, "Precision": [1.0, 0.5], "Recall": 1.0, "F1": 1.0, "Learning time": 4.342868740081787, "parameter": {"AUC ROC": 0.5, "AUC PR": 0.047837, "CLL": -0.408752, "Precision": [NaN, 0.5], "Recall": 0.0, "F1": NaN}, "Mapping time": 0.015455961227416992}, "transfer_0.6": {"AUC ROC": 1.0, "AUC PR": 1.0, "CLL": -0.077944, "Precision": [1.0, 0.5], "Recall": 1.0, "F1": 1.0, "Learning time": 5.018593078613281, "parameter": {"AUC ROC": 0.5, "AUC PR": 0.047837, "CLL": -0.409891, "Precision": [NaN, 0.5], "Recall": 0.0, "F1": NaN}, "Mapping time": 0.015455961227416992}, "transfer_0.8": {"AUC ROC": 1.0, "AUC PR": 1.0, "CLL": -0.074368, "Precision": [1.0, 0.5], "Recall": 1.0, "F1": 1.0, "Learning time": 5.616264610290527, "parameter": {"AUC ROC": 0.5, "AUC PR": 0.047837, "CLL": -0.418744, "Precision": [NaN, 0.5], "Recall": 0.0, "F1": NaN}, "Mapping time": 0.015455961227416992}, "transfer_1.0": {"AUC ROC": 1.0, "AUC PR": 1.0, "CLL": -0.06789, "Precision": [1.0, 0.5], "Recall": 1.0, "F1": 1.0, "Learning time": 6.263454860687256, "parameter": {"AUC ROC": 0.5, "AUC PR": 0.047837, "CLL": -0.401801, "Precision": [NaN, 0.5], "Recall": 0.0, "F1": NaN}, "Mapping time": 0.015455961227416992}}, {"transfer_0.2": {"AUC ROC": 1.0, "AUC PR": 1.0, "CLL": -0.063847, "Precision": [1.0, 0.5], "Recall": 1.0, "F1": 1.0, "Learning time": 3.9088652515411377, "parameter": {"AUC ROC": 0.5, "AUC PR": 0.023244, "CLL": -0.369913, "Precision": [NaN, 0.5], "Recall": 0.0, "F1": NaN}, "Mapping time": 0.015455961227416992}, "transfer_0.4": {"AUC ROC": 1.0, "AUC PR": 1.0, "CLL": -0.063847, "Precision": [1.0, 0.5], "Recall": 1.0, "F1": 1.0, "Learning time": 4.904963228225708, "parameter": {"AUC ROC": 0.5, "AUC PR": 0.023244, "CLL": -0.391746, "Precision": [NaN, 0.5], "Recall": 0.0, "F1": NaN}, "Mapping time": 0.015455961227416992}, "transfer_0.6": {"AUC ROC": 1.0, "AUC PR": 1.0, "CLL": -0.063847, "Precision": [1.0, 0.5], "Recall": 1.0, "F1": 1.0, "Learning time": 5.8385662174224855, "parameter": {"AUC ROC": 0.5, "AUC PR": 0.023244, "CLL": -0.383804, "Precision": [NaN, 0.5], "Recall": 0.0, "F1": NaN}, "Mapping time": 0.015455961227416992}, "transfer_0.8": {"AUC ROC": 1.0, "AUC PR": 1.0, "CLL": -0.063847, "Precision": [1.0, 0.5], "Recall": 1.0, "F1": 1.0, "Learning time": 6.745784149169921, "parameter": {"AUC ROC": 0.5, "AUC PR": 0.023244, "CLL": -0.380879, "Precision": [NaN, 0.5], "Recall": 0.0, "F1": NaN}, "Mapping time": 0.015455961227416992}, "transfer_1.0": {"AUC ROC": 1.0, "AUC PR": 1.0, "CLL": -0.063847, "Precision": [1.0, 0.5], "Recall": 1.0, "F1": 1.0, "Learning time": 7.358525669097901, "parameter": {"AUC ROC": 0.5, "AUC PR": 0.023244, "CLL": -0.381338, "Precision": [NaN, 0.5], "Recall": 0.0, "F1": NaN}, "Mapping time": 0.015455961227416992}}, {"transfer_0.2": {"AUC ROC": 1.0, "AUC PR": 1.0, "CLL": -0.0637, "Precision": [1.0, 0.5], "Recall": 1.0, "F1": 1.0, "Learning time": 4.025250398635864, "parameter": {"AUC ROC": 0.5, "AUC PR": 0.021267, "CLL": -0.39532, "Precision": [NaN, 0.5], "Recall": 0.0, "F1": NaN}, "Mapping time": 0.015455961227416992}, "transfer_0.4": {"AUC ROC": 1.0, "AUC PR": 1.0, "CLL": -0.063719, "Precision": [1.0, 0.5], "Recall": 1.0, "F1": 1.0, "Learning time": 4.942584386825562, "parameter": {"AUC ROC": 0.5, "AUC PR": 0.021267, "CLL": -0.383541, "Precision": [NaN, 0.5], "Recall": 0.0, "F1": NaN}, "Mapping time": 0.015455961227416992}, "transfer_0.6": {"AUC ROC": 1.0, "AUC PR": 1.0, "CLL": -0.063719, "Precision": [1.0, 0.5], "Recall": 1.0, "F1": 1.0, "Learning time": 5.735596157073974, "parameter": {"AUC ROC": 0.5, "AUC PR": 0.021267, "CLL": -0.385839, "Precision": [NaN, 0.5], "Recall": 0.0, "F1": NaN}, "Mapping time": 0.015455961227416992}, "transfer_0.8": {"AUC ROC": 1.0, "AUC PR": 1.0, "CLL": -0.063719, "Precision": [1.0, 0.5], "Recall": 1.0, "F1": 1.0, "Learning time": 6.34665408706665, "parameter": {"AUC ROC": 0.5, "AUC PR": 0.021267, "CLL": -0.389034, "Precision": [NaN, 0.5], "Recall": 0.0, "F1": NaN}, "Mapping time": 0.015455961227416992}, "transfer_1.0": {"AUC ROC": 1.0, "AUC PR": 1.0, "CLL": -0.063719, "Precision": [1.0, 0.5], "Recall": 1.0, "F1": 1.0, "Learning time": 7.777716146469116, "parameter": {"AUC ROC": 0.5, "AUC PR": 0.021267, "CLL": -0.390509, "Precision": [NaN, 0.5], "Recall": 0.0, "F1": NaN}, "Mapping time": 0.015455961227416992}}], [{"transfer_0.2": {"AUC ROC": 1.0, "AUC PR": 1.0, "CLL": -0.063421, "Precision": [1.0, 0.5], "Recall": 1.0, "F1": 1.0, "Learning time": 4.021305400848389, "parameter": {"AUC ROC": 0.5, "AUC PR": 0.016647, "CLL": -0.383316, "Precision": [NaN, 0.5], "Recall": 0.0, "F1": NaN}, "Mapping time": 0.014913558959960938}, "transfer_0.4": {"AUC ROC": 1.0, "AUC PR": 1.0, "CLL": -0.063421, "Precision": [1.0, 0.5], "Recall": 1.0, "F1": 1.0, "Learning time": 4.802578248977661, "parameter": {"AUC ROC": 0.5, "AUC PR": 0.016647, "CLL": -0.380118, "Precision": [NaN, 0.5], "Recall": 0.0, "F1": NaN}, "Mapping time": 0.014913558959960938}, "transfer_0.6": {"AUC ROC": 1.0, "AUC PR": 1.0, "CLL": -0.063421, "Precision": [1.0, 0.5], "Recall": 1.0, "F1": 1.0, "Learning time": 5.552745809555054, "parameter": {"AUC ROC": 0.5, "AUC PR": 0.016647, "CLL": -0.375292, "Precision": [NaN, 0.5], "Recall": 0.0, "F1": NaN}, "Mapping time": 0.014913558959960938}, "transfer_0.8": {"AUC ROC": 1.0, "AUC PR": 1.0, "CLL": -0.063421, "Precision": [1.0, 0.5], "Recall": 1.0, "F1": 1.0, "Learning time": 6.509696886062622, "parameter": {"AUC ROC": 0.5, "AUC PR": 0.016647, "CLL": -0.378202, "Precision": [NaN, 0.5], "Recall": 0.0, "F1": NaN}, "Mapping time": 0.014913558959960938}, "transfer_1.0": {"AUC ROC": 1.0, "AUC PR": 1.0, "CLL": -0.06339, "Precision": [1.0, 0.5], "Recall": 1.0, "F1": 1.0, "Learning time": 7.127294734954834, "parameter": {"AUC ROC": 0.5, "AUC PR": 0.016647, "CLL": -0.372526, "Precision": [NaN, 0.5], "Recall": 0.0, "F1": NaN}, "Mapping time": 0.014913558959960938}}, {"transfer_0.2": {"AUC ROC": 1.0, "AUC PR": 1.0, "CLL": -0.063422, "Precision": [1.0, 0.5], "Recall": 1.0, "F1": 1.0, "Learning time": 3.8597635765075684, "parameter": {"AUC ROC": 0.5, "AUC PR": 0.016662, "CLL": -0.401911, "Precision": [NaN, 0.5], "Recall": 0.0, "F1": NaN}, "Mapping time": 0.014913558959960938}, "transfer_0.4": {"AUC ROC": 1.0, "AUC PR": 1.0, "CLL": -0.063422, "Precision": [1.0, 0.5], "Recall": 1.0, "F1": 1.0, "Learning time": 4.890122270584106, "parameter": {"AUC ROC": 0.5, "AUC PR": 0.016662, "CLL": -0.376398, "Precision": [NaN, 0.5], "Recall": 0.0, "F1": NaN}, "Mapping time": 0.014913558959960938}, "transfer_0.6": {"AUC ROC": 1.0, "AUC PR": 1.0, "CLL": -0.063422, "Precision": [1.0, 0.5], "Recall": 1.0, "F1": 1.0, "Learning time": 5.705660860061646, "parameter": {"AUC ROC": 0.5, "AUC PR": 0.016662, "CLL": -0.386864, "Precision": [NaN, 0.5], "Recall": 0.0, "F1": NaN}, "Mapping time": 0.014913558959960938}, "transfer_0.8": {"AUC ROC": 1.0, "AUC PR": 1.0, "CLL": -0.063422, "Precision": [1.0, 0.5], "Recall": 1.0, "F1": 1.0, "Learning time": 6.544552392959595, "parameter": {"AUC ROC": 0.5, "AUC PR": 0.016662, "CLL": -0.383455, "Precision": [NaN, 0.5], "Recall": 0.0, "F1": NaN}, "Mapping time": 0.014913558959960938}, "transfer_1.0": {"AUC ROC": 1.0, "AUC PR": 1.0, "CLL": -0.063422, "Precision": [1.0, 0.5], "Recall": 1.0, "F1": 1.0, "Learning time": 7.228414609909057, "parameter": {"AUC ROC": 0.5, "AUC PR": 0.016662, "CLL": -0.380737, "Precision": [NaN, 0.5], "Recall": 0.0, "F1": NaN}, "Mapping time": 0.014913558959960938}}, {"transfer_0.2": {"AUC ROC": 1.0, "AUC PR": 1.0, "CLL": -0.095236, "Precision": [1.0, 0.5], "Recall": 1.0, "F1": 1.0, "Learning time": 3.611493246078491, "parameter": {"AUC ROC": 0.5, "AUC PR": 0.047837, "CLL": -0.402814, "Precision": [NaN, 0.5], "Recall": 0.0, "F1": NaN}, "Mapping time": 0.014913558959960938}, "transfer_0.4": {"AUC ROC": 1.0, "AUC PR": 1.0, "CLL": -0.073474, "Precision": [1.0, 0.5], "Recall": 1.0, "F1": 1.0, "Learning time": 4.249579923629761, "parameter": {"AUC ROC": 0.5, "AUC PR": 0.047837, "CLL": -0.402622, "Precision": [NaN, 0.5], "Recall": 0.0, "F1": NaN}, "Mapping time": 0.014913558959960938}, "transfer_0.6": {"AUC ROC": 1.0, "AUC PR": 1.0, "CLL": -0.06696, "Precision": [1.0, 0.5], "Recall": 1.0, "F1": 1.0, "Learning time": 5.0368464584350585, "parameter": {"AUC ROC": 0.5, "AUC PR": 0.047837, "CLL": -0.406516, "Precision": [NaN, 0.5], "Recall": 0.0, "F1": NaN}, "Mapping time": 0.014913558959960938}, "transfer_0.8": {"AUC ROC": 1.0, "AUC PR": 1.0, "CLL": -0.066393, "Precision": [1.0, 0.5], "Recall": 1.0, "F1": 1.0, "Learning time": 5.541594375610352, "parameter": {"AUC ROC": 0.5, "AUC PR": 0.047837, "CLL": -0.404259, "Precision": [NaN, 0.5], "Recall": 0.0, "F1": NaN}, "Mapping time": 0.014913558959960938}, "transfer_1.0": {"AUC ROC": 1.0, "AUC PR": 1.0, "CLL": -0.06947, "Precision": [1.0, 0.5], "Recall": 1.0, "F1": 1.0, "Learning time": 6.190442886352539, "parameter": {"AUC ROC": 0.5, "AUC PR": 0.047837, "CLL": -0.402943, "Precision": [NaN, 0.5], "Recall": 0.0, "F1": NaN}, "Mapping time": 0.014913558959960938}}, {"transfer_0.2": {"AUC ROC": 1.0, "AUC PR": 1.0, "CLL": -0.063847, "Precision": [1.0, 0.5], "Recall": 1.0, "F1": 1.0, "Learning time": 3.887080141067505, "parameter": {"AUC ROC": 0.5, "AUC PR": 0.023244, "CLL": -0.381276, "Precision": [NaN, 0.5], "Recall": 0.0, "F1": NaN}, "Mapping time": 0.014913558959960938}, "transfer_0.4": {"AUC ROC": 1.0, "AUC PR": 1.0, "CLL": -0.063847, "Precision": [1.0, 0.5], "Recall": 1.0, "F1": 1.0, "Learning time": 4.918294052124024, "parameter": {"AUC ROC": 0.5, "AUC PR": 0.023244, "CLL": -0.388944, "Precision": [NaN, 0.5], "Recall": 0.0, "F1": NaN}, "Mapping time": 0.014913558959960938}, "transfer_0.6": {"AUC ROC": 1.0, "AUC PR": 1.0, "CLL": -0.063847, "Precision": [1.0, 0.5], "Recall": 1.0, "F1": 1.0, "Learning time": 5.838385223388672, "parameter": {"AUC ROC": 0.5, "AUC PR": 0.023244, "CLL": -0.383463, "Precision": [NaN, 0.5], "Recall": 0.0, "F1": NaN}, "Mapping time": 0.014913558959960938}, "transfer_0.8": {"AUC ROC": 1.0, "AUC PR": 1.0, "CLL": -0.063847, "Precision": [1.0, 0.5], "Recall": 1.0, "F1": 1.0, "Learning time": 6.722626588821411, "parameter": {"AUC ROC": 0.5, "AUC PR": 0.023244, "CLL": -0.396769, "Precision": [NaN, 0.5], "Recall": 0.0, "F1": NaN}, "Mapping time": 0.014913558959960938}, "transfer_1.0": {"AUC ROC": 1.0, "AUC PR": 1.0, "CLL": -0.063847, "Precision": [1.0, 0.5], "Recall": 1.0, "F1": 1.0, "Learning time": 7.728102560043335, "parameter": {"AUC ROC": 0.5, "AUC PR": 0.023244, "CLL": -0.383071, "Precision": [NaN, 0.5], "Recall": 0.0, "F1": NaN}, "Mapping time": 0.014913558959960938}}, {"transfer_0.2": {"AUC ROC": 1.0, "AUC PR": 1.0, "CLL": -0.064262, "Precision": [1.0, 0.5], "Recall": 1.0, "F1": 1.0, "Learning time": 4.052573383331299, "parameter": {"AUC ROC": 0.5, "AUC PR": 0.021267, "CLL": -0.383753, "Precision": [NaN, 0.5], "Recall": 0.0, "F1": NaN}, "Mapping time": 0.014913558959960938}, "transfer_0.4": {"AUC ROC": 1.0, "AUC PR": 1.0, "CLL": -0.063719, "Precision": [1.0, 0.5], "Recall": 1.0, "F1": 1.0, "Learning time": 4.795320411682129, "parameter": {"AUC ROC": 0.5, "AUC PR": 0.021267, "CLL": -0.381987, "Precision": [NaN, 0.5], "Recall": 0.0, "F1": NaN}, "Mapping time": 0.014913558959960938}, "transfer_0.6": {"AUC ROC": 1.0, "AUC PR": 1.0, "CLL": -0.063719, "Precision": [1.0, 0.5], "Recall": 1.0, "F1": 1.0, "Learning time": 5.8124848690032955, "parameter": {"AUC ROC": 0.5, "AUC PR": 0.021267, "CLL": -0.383519, "Precision": [NaN, 0.5], "Recall": 0.0, "F1": NaN}, "Mapping time": 0.014913558959960938}, "transfer_0.8": {"AUC ROC": 1.0, "AUC PR": 1.0, "CLL": -0.063719, "Precision": [1.0, 0.5], "Recall": 1.0, "F1": 1.0, "Learning time": 6.616357681274414, "parameter": {"AUC ROC": 0.5, "AUC PR": 0.021267, "CLL": -0.382167, "Precision": [NaN, 0.5], "Recall": 0.0, "F1": NaN}, "Mapping time": 0.014913558959960938}, "transfer_1.0": {"AUC ROC": 1.0, "AUC PR": 1.0, "CLL": -0.063719, "Precision": [1.0, 0.5], "Recall": 1.0, "F1": 1.0, "Learning time": 7.435281446456909, "parameter": {"AUC ROC": 0.5, "AUC PR": 0.021267, "CLL": -0.388349, "Precision": [NaN, 0.5], "Recall": 0.0, "F1": NaN}, "Mapping time": 0.014913558959960938}}], [{"transfer_0.2": {"AUC ROC": 1.0, "AUC PR": 1.0, "CLL": -0.063411, "Precision": [1.0, 0.5], "Recall": 1.0, "F1": 1.0, "Learning time": 3.744012907028198, "parameter": {"AUC ROC": 0.5, "AUC PR": 0.016647, "CLL": -0.385672, "Precision": [NaN, 0.5], "Recall": 0.0, "F1": NaN}, "Mapping time": 0.015509843826293945}, "transfer_0.4": {"AUC ROC": 1.0, "AUC PR": 1.0, "CLL": -0.063036, "Precision": [1.0, 0.5], "Recall": 1.0, "F1": 1.0, "Learning time": 4.879975109100342, "parameter": {"AUC ROC": 0.5, "AUC PR": 0.016647, "CLL": -0.380978, "Precision": [NaN, 0.5], "Recall": 0.0, "F1": NaN}, "Mapping time": 0.015509843826293945}, "transfer_0.6": {"AUC ROC": 1.0, "AUC PR": 1.0, "CLL": -0.063421, "Precision": [1.0, 0.5], "Recall": 1.0, "F1": 1.0, "Learning time": 5.723057195663452, "parameter": {"AUC ROC": 0.5, "AUC PR": 0.016647, "CLL": -0.381356, "Precision": [NaN, 0.5], "Recall": 0.0, "F1": NaN}, "Mapping time": 0.015509843826293945}, "transfer_0.8": {"AUC ROC": 1.0, "AUC PR": 1.0, "CLL": -0.063421, "Precision": [1.0, 0.5], "Recall": 1.0, "F1": 1.0, "Learning time": 6.654131563186645, "parameter": {"AUC ROC": 0.5, "AUC PR": 0.016647, "CLL": -0.383375, "Precision": [NaN, 0.5], "Recall": 0.0, "F1": NaN}, "Mapping time": 0.015509843826293945}, "transfer_1.0": {"AUC ROC": 1.0, "AUC PR": 1.0, "CLL": -0.063421, "Precision": [1.0, 0.5], "Recall": 1.0, "F1": 1.0, "Learning time": 7.33404433631897, "parameter": {"AUC ROC": 0.5, "AUC PR": 0.016647, "CLL": -0.378233, "Precision": [NaN, 0.5], "Recall": 0.0, "F1": NaN}, "Mapping time": 0.015509843826293945}}, {"transfer_0.2": {"AUC ROC": 1.0, "AUC PR": 1.0, "CLL": -0.063422, "Precision": [1.0, 0.5], "Recall": 1.0, "F1": 1.0, "Learning time": 4.11487896156311, "parameter": {"AUC ROC": 0.5, "AUC PR": 0.016662, "CLL": -0.384052, "Precision": [NaN, 0.5], "Recall": 0.0, "F1": NaN}, "Mapping time": 0.015509843826293945}, "transfer_0.4": {"AUC ROC": 1.0, "AUC PR": 1.0, "CLL": -0.063422, "Precision": [1.0, 0.5], "Recall": 1.0, "F1": 1.0, "Learning time": 4.6144564266204835, "parameter": {"AUC ROC": 0.5, "AUC PR": 0.016662, "CLL": -0.384324, "Precision": [NaN, 0.5], "Recall": 0.0, "F1": NaN}, "Mapping time": 0.015509843826293945}, "transfer_0.6": {"AUC ROC": 1.0, "AUC PR": 1.0, "CLL": -0.063422, "Precision": [1.0, 0.5], "Recall": 1.0, "F1": 1.0, "Learning time": 5.689638774871826, "parameter": {"AUC ROC": 0.5, "AUC PR": 0.016662, "CLL": -0.374069, "Precision": [NaN, 0.5], "Recall": 0.0, "F1": NaN}, "Mapping time": 0.015509843826293945}, "transfer_0.8": {"AUC ROC": 1.0, "AUC PR": 1.0, "CLL": -0.063422, "Precision": [1.0, 0.5], "Recall": 1.0, "F1": 1.0, "Learning time": 6.40709750366211, "parameter": {"AUC ROC": 0.5, "AUC PR": 0.016662, "CLL": -0.393482, "Precision": [NaN, 0.5], "Recall": 0.0, "F1": NaN}, "Mapping time": 0.015509843826293945}, "transfer_1.0": {"AUC ROC": 1.0, "AUC PR": 1.0, "CLL": -0.063422, "Precision": [1.0, 0.5], "Recall": 1.0, "F1": 1.0, "Learning time": 7.1827289066314695, "parameter": {"AUC ROC": 0.5, "AUC PR": 0.016662, "CLL": -0.380607, "Precision": [NaN, 0.5], "Recall": 0.0, "F1": NaN}, "Mapping time": 0.015509843826293945}}, {"transfer_0.2": {"AUC ROC": 1.0, "AUC PR": 1.0, "CLL": -0.112421, "Precision": [0.626761, 0.5], "Recall": 1.0, "F1": 0.770563, "Learning time": 3.6737438945770267, "parameter": {"AUC ROC": 0.5, "AUC PR": 0.047837, "CLL": -0.392317, "Precision": [NaN, 0.5], "Recall": 0.0, "F1": NaN}, "Mapping time": 0.015509843826293945}, "transfer_0.4": {"AUC ROC": 1.0, "AUC PR": 1.0, "CLL": -0.072176, "Precision": [1.0, 0.5], "Recall": 1.0, "F1": 1.0, "Learning time": 4.389626731872559, "parameter": {"AUC ROC": 0.5, "AUC PR": 0.047837, "CLL": -0.406148, "Precision": [NaN, 0.5], "Recall": 0.0, "F1": NaN}, "Mapping time": 0.015509843826293945}, "transfer_0.6": {"AUC ROC": 1.0, "AUC PR": 1.0, "CLL": -0.0709, "Precision": [1.0, 0.5], "Recall": 1.0, "F1": 1.0, "Learning time": 5.040658151626587, "parameter": {"AUC ROC": 0.5, "AUC PR": 0.047837, "CLL": -0.415254, "Precision": [NaN, 0.5], "Recall": 0.0, "F1": NaN}, "Mapping time": 0.015509843826293945}, "transfer_0.8": {"AUC ROC": 1.0, "AUC PR": 1.0, "CLL": -0.06855, "Precision": [1.0, 0.5], "Recall": 1.0, "F1": 1.0, "Learning time": 5.630188959121704, "parameter": {"AUC ROC": 0.5, "AUC PR": 0.047837, "CLL": -0.400843, "Precision": [NaN, 0.5], "Recall": 0.0, "F1": NaN}, "Mapping time": 0.015509843826293945}, "transfer_1.0": {"AUC ROC": 1.0, "AUC PR": 1.0, "CLL": -0.066116, "Precision": [1.0, 0.5], "Recall": 1.0, "F1": 1.0, "Learning time": 6.274182678222656, "parameter": {"AUC ROC": 0.5, "AUC PR": 0.047837, "CLL": -0.41052, "Precision": [NaN, 0.5], "Recall": 0.0, "F1": NaN}, "Mapping time": 0.015509843826293945}}, {"transfer_0.2": {"AUC ROC": 1.0, "AUC PR": 1.0, "CLL": -0.063889, "Precision": [1.0, 0.5], "Recall": 1.0, "F1": 1.0, "Learning time": 4.215803344726563, "parameter": {"AUC ROC": 0.5, "AUC PR": 0.023244, "CLL": -0.37993, "Precision": [NaN, 0.5], "Recall": 0.0, "F1": NaN}, "Mapping time": 0.015509843826293945}, "transfer_0.4": {"AUC ROC": 1.0, "AUC PR": 1.0, "CLL": -0.063847, "Precision": [1.0, 0.5], "Recall": 1.0, "F1": 1.0, "Learning time": 5.161024827957153, "parameter": {"AUC ROC": 0.5, "AUC PR": 0.023244, "CLL": -0.39086, "Precision": [NaN, 0.5], "Recall": 0.0, "F1": NaN}, "Mapping time": 0.015509843826293945}, "transfer_0.6": {"AUC ROC": 1.0, "AUC PR": 1.0, "CLL": -0.063842, "Precision": [1.0, 0.5], "Recall": 1.0, "F1": 1.0, "Learning time": 6.044381994247436, "parameter": {"AUC ROC": 0.5, "AUC PR": 0.023244, "CLL": -0.381009, "Precision": [NaN, 0.5], "Recall": 0.0, "F1": NaN}, "Mapping time": 0.015509843826293945}, "transfer_0.8": {"AUC ROC": 1.0, "AUC PR": 1.0, "CLL": -0.063847, "Precision": [1.0, 0.5], "Recall": 1.0, "F1": 1.0, "Learning time": 6.4349063205718995, "parameter": {"AUC ROC": 0.5, "AUC PR": 0.023244, "CLL": -0.385917, "Precision": [NaN, 0.5], "Recall": 0.0, "F1": NaN}, "Mapping time": 0.015509843826293945}, "transfer_1.0": {"AUC ROC": 1.0, "AUC PR": 1.0, "CLL": -0.063872, "Precision": [1.0, 0.5], "Recall": 1.0, "F1": 1.0, "Learning time": 7.559555273056031, "parameter": {"AUC ROC": 0.5, "AUC PR": 0.023244, "CLL": -0.38603, "Precision": [NaN, 0.5], "Recall": 0.0, "F1": NaN}, "Mapping time": 0.015509843826293945}}, {"transfer_0.2": {"AUC ROC": 1.0, "AUC PR": 1.0, "CLL": -0.063719, "Precision": [1.0, 0.5], "Recall": 1.0, "F1": 1.0, "Learning time": 4.072399694442749, "parameter": {"AUC ROC": 0.5, "AUC PR": 0.021267, "CLL": -0.383647, "Precision": [NaN, 0.5], "Recall": 0.0, "F1": NaN}, "Mapping time": 0.015509843826293945}, "transfer_0.4": {"AUC ROC": 1.0, "AUC PR": 1.0, "CLL": -0.063719, "Precision": [1.0, 0.5], "Recall": 1.0, "F1": 1.0, "Learning time": 4.927972820281982, "parameter": {"AUC ROC": 0.5, "AUC PR": 0.021267, "CLL": -0.384722, "Precision": [NaN, 0.5], "Recall": 0.0, "F1": NaN}, "Mapping time": 0.015509843826293945}, "transfer_0.6": {"AUC ROC": 1.0, "AUC PR": 1.0, "CLL": -0.063719, "Precision": [1.0, 0.5], "Recall": 1.0, "F1": 1.0, "Learning time": 5.755746927261352, "parameter": {"AUC ROC": 0.5, "AUC PR": 0.021267, "CLL": -0.390518, "Precision": [NaN, 0.5], "Recall": 0.0, "F1": NaN}, "Mapping time": 0.015509843826293945}, "transfer_0.8": {"AUC ROC": 1.0, "AUC PR": 1.0, "CLL": -0.063719, "Precision": [1.0, 0.5], "Recall": 1.0, "F1": 1.0, "Learning time": 6.736188903808594, "parameter": {"AUC ROC": 0.5, "AUC PR": 0.021267, "CLL": -0.390222, "Precision": [NaN, 0.5], "Recall": 0.0, "F1": NaN}, "Mapping time": 0.015509843826293945}, "transfer_1.0": {"AUC ROC": 1.0, "AUC PR": 1.0, "CLL": -0.063719, "Precision": [1.0, 0.5], "Recall": 1.0, "F1": 1.0, "Learning time": 7.53106343460083, "parameter": {"AUC ROC": 0.5, "AUC PR": 0.021267, "CLL": -0.382325, "Precision": [NaN, 0.5], "Recall": 0.0, "F1": NaN}, "Mapping time": 0.015509843826293945}}], [{"transfer_0.2": {"AUC ROC": 1.0, "AUC PR": 1.0, "CLL": -0.062816, "Precision": [1.0, 0.5], "Recall": 1.0, "F1": 1.0, "Learning time": 3.8560099353790283, "parameter": {"AUC ROC": 0.5, "AUC PR": 0.016647, "CLL": -0.387579, "Precision": [NaN, 0.5], "Recall": 0.0, "F1": NaN}, "Mapping time": 0.014829874038696289}, "transfer_0.4": {"AUC ROC": 1.0, "AUC PR": 1.0, "CLL": -0.063436, "Precision": [1.0, 0.5], "Recall": 1.0, "F1": 1.0, "Learning time": 4.85086209487915, "parameter": {"AUC ROC": 0.5, "AUC PR": 0.016647, "CLL": -0.365576, "Precision": [NaN, 0.5], "Recall": 0.0, "F1": NaN}, "Mapping time": 0.014829874038696289}, "transfer_0.6": {"AUC ROC": 1.0, "AUC PR": 1.0, "CLL": -0.063421, "Precision": [1.0, 0.5], "Recall": 1.0, "F1": 1.0, "Learning time": 5.904629261016845, "parameter": {"AUC ROC": 0.5, "AUC PR": 0.016647, "CLL": -0.378323, "Precision": [NaN, 0.5], "Recall": 0.0, "F1": NaN}, "Mapping time": 0.014829874038696289}, "transfer_0.8": {"AUC ROC": 1.0, "AUC PR": 1.0, "CLL": -0.063421, "Precision": [1.0, 0.5], "Recall": 1.0, "F1": 1.0, "Learning time": 6.868812446594238, "parameter": {"AUC ROC": 0.5, "AUC PR": 0.016647, "CLL": -0.380648, "Precision": [NaN, 0.5], "Recall": 0.0, "F1": NaN}, "Mapping time": 0.014829874038696289}, "transfer_1.0": {"AUC ROC": 1.0, "AUC PR": 1.0, "CLL": -0.063421, "Precision": [1.0, 0.5], "Recall": 1.0, "F1": 1.0, "Learning time": 7.166324575424195, "parameter": {"AUC ROC": 0.5, "AUC PR": 0.016647, "CLL": -0.380474, "Precision": [NaN, 0.5], "Recall": 0.0, "F1": NaN}, "Mapping time": 0.014829874038696289}}, {"transfer_0.2": {"AUC ROC": 1.0, "AUC PR": 1.0, "CLL": -0.063422, "Precision": [1.0, 0.5], "Recall": 1.0, "F1": 1.0, "Learning time": 3.88737756729126, "parameter": {"AUC ROC": 0.5, "AUC PR": 0.016662, "CLL": -0.371174, "Precision": [NaN, 0.5], "Recall": 0.0, "F1": NaN}, "Mapping time": 0.014829874038696289}, "transfer_0.4": {"AUC ROC": 1.0, "AUC PR": 1.0, "CLL": -0.063422, "Precision": [1.0, 0.5], "Recall": 1.0, "F1": 1.0, "Learning time": 4.89847290802002, "parameter": {"AUC ROC": 0.5, "AUC PR": 0.016662, "CLL": -0.385658, "Precision": [NaN, 0.5], "Recall": 0.0, "F1": NaN}, "Mapping time": 0.014829874038696289}, "transfer_0.6": {"AUC ROC": 1.0, "AUC PR": 1.0, "CLL": -0.063422, "Precision": [1.0, 0.5], "Recall": 1.0, "F1": 1.0, "Learning time": 5.714055017471313, "parameter": {"AUC ROC": 0.5, "AUC PR": 0.016662, "CLL": -0.387467, "Precision": [NaN, 0.5], "Recall": 0.0, "F1": NaN}, "Mapping time": 0.014829874038696289}, "transfer_0.8": {"AUC ROC": 1.0, "AUC PR": 1.0, "CLL": -0.063422, "Precision": [1.0, 0.5], "Recall": 1.0, "F1": 1.0, "Learning time": 6.384248428344726, "parameter": {"AUC ROC": 0.5, "AUC PR": 0.016662, "CLL": -0.384765, "Precision": [NaN, 0.5], "Recall": 0.0, "F1": NaN}, "Mapping time": 0.014829874038696289}, "transfer_1.0": {"AUC ROC": 1.0, "AUC PR": 1.0, "CLL": -0.063422, "Precision": [1.0, 0.5], "Recall": 1.0, "F1": 1.0, "Learning time": 7.3006016101837155, "parameter": {"AUC ROC": 0.5, "AUC PR": 0.016662, "CLL": -0.384097, "Precision": [NaN, 0.5], "Recall": 0.0, "F1": NaN}, "Mapping time": 0.014829874038696289}}, {"transfer_0.2": {"AUC ROC": 1.0, "AUC PR": 1.0, "CLL": -0.129163, "Precision": [0.626761, 0.5], "Recall": 1.0, "F1": 0.770563, "Learning time": 3.615690362930298, "parameter": {"AUC ROC": 0.5, "AUC PR": 0.047837, "CLL": -0.401403, "Precision": [NaN, 0.5], "Recall": 0.0, "F1": NaN}, "Mapping time": 0.014829874038696289}, "transfer_0.4": {"AUC ROC": 1.0, "AUC PR": 1.0, "CLL": -0.091743, "Precision": [0.626761, 0.5], "Recall": 1.0, "F1": 0.770563, "Learning time": 4.463941562652588, "parameter": {"AUC ROC": 0.5, "AUC PR": 0.047837, "CLL": -0.411479, "Precision": [NaN, 0.5], "Recall": 0.0, "F1": NaN}, "Mapping time": 0.014829874038696289}, "transfer_0.6": {"AUC ROC": 1.0, "AUC PR": 1.0, "CLL": -0.070495, "Precision": [1.0, 0.5], "Recall": 1.0, "F1": 1.0, "Learning time": 5.1216526699066165, "parameter": {"AUC ROC": 0.5, "AUC PR": 0.047837, "CLL": -0.408191, "Precision": [NaN, 0.5], "Recall": 0.0, "F1": NaN}, "Mapping time": 0.014829874038696289}, "transfer_0.8": {"AUC ROC": 1.0, "AUC PR": 1.0, "CLL": -0.066565, "Precision": [1.0, 0.5], "Recall": 1.0, "F1": 1.0, "Learning time": 5.701831857681274, "parameter": {"AUC ROC": 0.5, "AUC PR": 0.047837, "CLL": -0.408601, "Precision": [NaN, 0.5], "Recall": 0.0, "F1": NaN}, "Mapping time": 0.014829874038696289}, "transfer_1.0": {"AUC ROC": 1.0, "AUC PR": 1.0, "CLL": -0.067285, "Precision": [1.0, 0.5], "Recall": 1.0, "F1": 1.0, "Learning time": 6.447085327148438, "parameter": {"AUC ROC": 0.5, "AUC PR": 0.047837, "CLL": -0.412248, "Precision": [NaN, 0.5], "Recall": 0.0, "F1": NaN}, "Mapping time": 0.014829874038696289}}, {"transfer_0.2": {"AUC ROC": 1.0, "AUC PR": 1.0, "CLL": -0.063847, "Precision": [1.0, 0.5], "Recall": 1.0, "F1": 1.0, "Learning time": 3.9418169231414795, "parameter": {"AUC ROC": 0.5, "AUC PR": 0.023244, "CLL": -0.406295, "Precision": [NaN, 0.5], "Recall": 0.0, "F1": NaN}, "Mapping time": 0.014829874038696289}, "transfer_0.4": {"AUC ROC": 1.0, "AUC PR": 1.0, "CLL": -0.063668, "Precision": [1.0, 0.5], "Recall": 1.0, "F1": 1.0, "Learning time": 5.076103420257569, "parameter": {"AUC ROC": 0.5, "AUC PR": 0.023244, "CLL": -0.377144, "Precision": [NaN, 0.5], "Recall": 0.0, "F1": NaN}, "Mapping time": 0.014829874038696289}, "transfer_0.6": {"AUC ROC": 1.0, "AUC PR": 1.0, "CLL": -0.063847, "Precision": [1.0, 0.5], "Recall": 1.0, "F1": 1.0, "Learning time": 5.920615320205688, "parameter": {"AUC ROC": 0.5, "AUC PR": 0.023244, "CLL": -0.379259, "Precision": [NaN, 0.5], "Recall": 0.0, "F1": NaN}, "Mapping time": 0.014829874038696289}, "transfer_0.8": {"AUC ROC": 1.0, "AUC PR": 1.0, "CLL": -0.063847, "Precision": [1.0, 0.5], "Recall": 1.0, "F1": 1.0, "Learning time": 6.6837965087890625, "parameter": {"AUC ROC": 0.5, "AUC PR": 0.023244, "CLL": -0.389738, "Precision": [NaN, 0.5], "Recall": 0.0, "F1": NaN}, "Mapping time": 0.014829874038696289}, "transfer_1.0": {"AUC ROC": 1.0, "AUC PR": 1.0, "CLL": -0.063847, "Precision": [1.0, 0.5], "Recall": 1.0, "F1": 1.0, "Learning time": 7.498897228240967, "parameter": {"AUC ROC": 0.5, "AUC PR": 0.023244, "CLL": -0.380763, "Precision": [NaN, 0.5], "Recall": 0.0, "F1": NaN}, "Mapping time": 0.014829874038696289}}, {"transfer_0.2": {"AUC ROC": 1.0, "AUC PR": 1.0, "CLL": -0.063719, "Precision": [1.0, 0.5], "Recall": 1.0, "F1": 1.0, "Learning time": 4.149134353637695, "parameter": {"AUC ROC": 0.5, "AUC PR": 0.021267, "CLL": -0.382937, "Precision": [NaN, 0.5], "Recall": 0.0, "F1": NaN}, "Mapping time": 0.014829874038696289}, "transfer_0.4": {"AUC ROC": 1.0, "AUC PR": 1.0, "CLL": -0.063719, "Precision": [1.0, 0.5], "Recall": 1.0, "F1": 1.0, "Learning time": 4.984870615005493, "parameter": {"AUC ROC": 0.5, "AUC PR": 0.021267, "CLL": -0.383728, "Precision": [NaN, 0.5], "Recall": 0.0, "F1": NaN}, "Mapping time": 0.014829874038696289}, "transfer_0.6": {"AUC ROC": 1.0, "AUC PR": 1.0, "CLL": -0.063719, "Precision": [1.0, 0.5], "Recall": 1.0, "F1": 1.0, "Learning time": 5.838403715133667, "parameter": {"AUC ROC": 0.5, "AUC PR": 0.021267, "CLL": -0.383639, "Precision": [NaN, 0.5], "Recall": 0.0, "F1": NaN}, "Mapping time": 0.014829874038696289}, "transfer_0.8": {"AUC ROC": 1.0, "AUC PR": 1.0, "CLL": -0.063719, "Precision": [1.0, 0.5], "Recall": 1.0, "F1": 1.0, "Learning time": 6.754938842773438, "parameter": {"AUC ROC": 0.5, "AUC PR": 0.021267, "CLL": -0.388702, "Precision": [NaN, 0.5], "Recall": 0.0, "F1": NaN}, "Mapping time": 0.014829874038696289}, "transfer_1.0": {"AUC ROC": 1.0, "AUC PR": 1.0, "CLL": -0.063719, "Precision": [1.0, 0.5], "Recall": 1.0, "F1": 1.0, "Learning time": 7.442966152191162, "parameter": {"AUC ROC": 0.5, "AUC PR": 0.021267, "CLL": -0.381176, "Precision": [NaN, 0.5], "Recall": 0.0, "F1": NaN}, "Mapping time": 0.014829874038696289}}], [{"transfer_0.2": {"AUC ROC": 1.0, "AUC PR": 1.0, "CLL": -0.063421, "Precision": [1.0, 0.5], "Recall": 1.0, "F1": 1.0, "Learning time": 3.938127166748047, "parameter": {"AUC ROC": 0.5, "AUC PR": 0.016647, "CLL": -0.379664, "Precision": [NaN, 0.5], "Recall": 0.0, "F1": NaN}, "Mapping time": 0.015005350112915039}, "transfer_0.4": {"AUC ROC": 1.0, "AUC PR": 1.0, "CLL": -0.063421, "Precision": [1.0, 0.5], "Recall": 1.0, "F1": 1.0, "Learning time": 4.839959930419922, "parameter": {"AUC ROC": 0.5, "AUC PR": 0.016647, "CLL": -0.391407, "Precision": [NaN, 0.5], "Recall": 0.0, "F1": NaN}, "Mapping time": 0.015005350112915039}, "transfer_0.6": {"AUC ROC": 1.0, "AUC PR": 1.0, "CLL": -0.063421, "Precision": [1.0, 0.5], "Recall": 1.0, "F1": 1.0, "Learning time": 5.849217342376709, "parameter": {"AUC ROC": 0.5, "AUC PR": 0.016647, "CLL": -0.37494, "Precision": [NaN, 0.5], "Recall": 0.0, "F1": NaN}, "Mapping time": 0.015005350112915039}, "transfer_0.8": {"AUC ROC": 1.0, "AUC PR": 1.0, "CLL": -0.063421, "Precision": [1.0, 0.5], "Recall": 1.0, "F1": 1.0, "Learning time": 6.596582746505738, "parameter": {"AUC ROC": 0.5, "AUC PR": 0.016647, "CLL": -0.385588, "Precision": [NaN, 0.5], "Recall": 0.0, "F1": NaN}, "Mapping time": 0.015005350112915039}, "transfer_1.0": {"AUC ROC": 1.0, "AUC PR": 1.0, "CLL": -0.063421, "Precision": [1.0, 0.5], "Recall": 1.0, "F1": 1.0, "Learning time": 7.3401816368103034, "parameter": {"AUC ROC": 0.5, "AUC PR": 0.016647, "CLL": -0.381145, "Precision": [NaN, 0.5], "Recall": 0.0, "F1": NaN}, "Mapping time": 0.015005350112915039}}, {"transfer_0.2": {"AUC ROC": 1.0, "AUC PR": 1.0, "CLL": -0.062763, "Precision": [1.0, 0.5], "Recall": 1.0, "F1": 1.0, "Learning time": 3.8597361373901364, "parameter": {"AUC ROC": 0.5, "AUC PR": 0.016662, "CLL": -0.369591, "Precision": [NaN, 0.5], "Recall": 0.0, "F1": NaN}, "Mapping time": 0.015005350112915039}, "transfer_0.4": {"AUC ROC": 1.0, "AUC PR": 1.0, "CLL": -0.063422, "Precision": [1.0, 0.5], "Recall": 1.0, "F1": 1.0, "Learning time": 4.906800605773926, "parameter": {"AUC ROC": 0.5, "AUC PR": 0.016662, "CLL": -0.39177, "Precision": [NaN, 0.5], "Recall": 0.0, "F1": NaN}, "Mapping time": 0.015005350112915039}, "transfer_0.6": {"AUC ROC": 1.0, "AUC PR": 1.0, "CLL": -0.063059, "Precision": [1.0, 0.5], "Recall": 1.0, "F1": 1.0, "Learning time": 5.634964859008789, "parameter": {"AUC ROC": 0.5, "AUC PR": 0.016662, "CLL": -0.376698, "Precision": [NaN, 0.5], "Recall": 0.0, "F1": NaN}, "Mapping time": 0.015005350112915039}, "transfer_0.8": {"AUC ROC": 1.0, "AUC PR": 1.0, "CLL": -0.063362, "Precision": [1.0, 0.5], "Recall": 1.0, "F1": 1.0, "Learning time": 6.527516693115235, "parameter": {"AUC ROC": 0.5, "AUC PR": 0.016662, "CLL": -0.383136, "Precision": [NaN, 0.5], "Recall": 0.0, "F1": NaN}, "Mapping time": 0.015005350112915039}, "transfer_1.0": {"AUC ROC": 1.0, "AUC PR": 1.0, "CLL": -0.063422, "Precision": [1.0, 0.5], "Recall": 1.0, "F1": 1.0, "Learning time": 7.354435026168823, "parameter": {"AUC ROC": 0.5, "AUC PR": 0.016662, "CLL": -0.377602, "Precision": [NaN, 0.5], "Recall": 0.0, "F1": NaN}, "Mapping time": 0.015005350112915039}}, {"transfer_0.2": {"AUC ROC": 1.0, "AUC PR": 1.0, "CLL": -0.125928, "Precision": [1.0, 0.5], "Recall": 1.0, "F1": 1.0, "Learning time": 3.6528033237457276, "parameter": {"AUC ROC": 0.5, "AUC PR": 0.047837, "CLL": -0.417218, "Precision": [NaN, 0.5], "Recall": 0.0, "F1": NaN}, "Mapping time": 0.015005350112915039}, "transfer_0.4": {"AUC ROC": 1.0, "AUC PR": 1.0, "CLL": -0.069252, "Precision": [1.0, 0.5], "Recall": 1.0, "F1": 1.0, "Learning time": 4.3073813838958745, "parameter": {"AUC ROC": 0.5, "AUC PR": 0.047837, "CLL": -0.408029, "Precision": [NaN, 0.5], "Recall": 0.0, "F1": NaN}, "Mapping time": 0.015005350112915039}, "transfer_0.6": {"AUC ROC": 1.0, "AUC PR": 1.0, "CLL": -0.073958, "Precision": [1.0, 0.5], "Recall": 1.0, "F1": 1.0, "Learning time": 4.896065721511841, "parameter": {"AUC ROC": 0.5, "AUC PR": 0.047837, "CLL": -0.397483, "Precision": [NaN, 0.5], "Recall": 0.0, "F1": NaN}, "Mapping time": 0.015005350112915039}, "transfer_0.8": {"AUC ROC": 1.0, "AUC PR": 1.0, "CLL": -0.072371, "Precision": [1.0, 0.5], "Recall": 1.0, "F1": 1.0, "Learning time": 5.6369833984375, "parameter": {"AUC ROC": 0.5, "AUC PR": 0.047837, "CLL": -0.410874, "Precision": [NaN, 0.5], "Recall": 0.0, "F1": NaN}, "Mapping time": 0.015005350112915039}, "transfer_1.0": {"AUC ROC": 1.0, "AUC PR": 1.0, "CLL": -0.068193, "Precision": [1.0, 0.5], "Recall": 1.0, "F1": 1.0, "Learning time": 6.3279812374115, "parameter": {"AUC ROC": 0.5, "AUC PR": 0.047837, "CLL": -0.409475, "Precision": [NaN, 0.5], "Recall": 0.0, "F1": NaN}, "Mapping time": 0.015005350112915039}}, {"transfer_0.2": {"AUC ROC": 1.0, "AUC PR": 1.0, "CLL": -0.063847, "Precision": [1.0, 0.5], "Recall": 1.0, "F1": 1.0, "Learning time": 4.0233730106353764, "parameter": {"AUC ROC": 0.5, "AUC PR": 0.023244, "CLL": -0.390538, "Precision": [NaN, 0.5], "Recall": 0.0, "F1": NaN}, "Mapping time": 0.015005350112915039}, "transfer_0.4": {"AUC ROC": 1.0, "AUC PR": 1.0, "CLL": -0.063847, "Precision": [1.0, 0.5], "Recall": 1.0, "F1": 1.0, "Learning time": 5.002206802368164, "parameter": {"AUC ROC": 0.5, "AUC PR": 0.023244, "CLL": -0.388035, "Precision": [NaN, 0.5], "Recall": 0.0, "F1": NaN}, "Mapping time": 0.015005350112915039}, "transfer_0.6": {"AUC ROC": 1.0, "AUC PR": 1.0, "CLL": -0.063714, "Precision": [1.0, 0.5], "Recall": 1.0, "F1": 1.0, "Learning time": 5.804963558197022, "parameter": {"AUC ROC": 0.5, "AUC PR": 0.023244, "CLL": -0.381231, "Precision": [NaN, 0.5], "Recall": 0.0, "F1": NaN}, "Mapping time": 0.015005350112915039}, "transfer_0.8": {"AUC ROC": 1.0, "AUC PR": 1.0, "CLL": -0.063847, "Precision": [1.0, 0.5], "Recall": 1.0, "F1": 1.0, "Learning time": 6.779600891113281, "parameter": {"AUC ROC": 0.5, "AUC PR": 0.023244, "CLL": -0.389826, "Precision": [NaN, 0.5], "Recall": 0.0, "F1": NaN}, "Mapping time": 0.015005350112915039}, "transfer_1.0": {"AUC ROC": 1.0, "AUC PR": 1.0, "CLL": -0.063847, "Precision": [1.0, 0.5], "Recall": 1.0, "F1": 1.0, "Learning time": 7.558134832382203, "parameter": {"AUC ROC": 0.5, "AUC PR": 0.023244, "CLL": -0.38912, "Precision": [NaN, 0.5], "Recall": 0.0, "F1": NaN}, "Mapping time": 0.015005350112915039}}, {"transfer_0.2": {"AUC ROC": 1.0, "AUC PR": 1.0, "CLL": -0.063719, "Precision": [1.0, 0.5], "Recall": 1.0, "F1": 1.0, "Learning time": 4.330700265884399, "parameter": {"AUC ROC": 0.5, "AUC PR": 0.021267, "CLL": -0.389801, "Precision": [NaN, 0.5], "Recall": 0.0, "F1": NaN}, "Mapping time": 0.015005350112915039}, "transfer_0.4": {"AUC ROC": 1.0, "AUC PR": 1.0, "CLL": -0.063719, "Precision": [1.0, 0.5], "Recall": 1.0, "F1": 1.0, "Learning time": 4.854031574249268, "parameter": {"AUC ROC": 0.5, "AUC PR": 0.021267, "CLL": -0.385781, "Precision": [NaN, 0.5], "Recall": 0.0, "F1": NaN}, "Mapping time": 0.015005350112915039}, "transfer_0.6": {"AUC ROC": 1.0, "AUC PR": 1.0, "CLL": -0.063719, "Precision": [1.0, 0.5], "Recall": 1.0, "F1": 1.0, "Learning time": 5.724246994018555, "parameter": {"AUC ROC": 0.5, "AUC PR": 0.021267, "CLL": -0.387884, "Precision": [NaN, 0.5], "Recall": 0.0, "F1": NaN}, "Mapping time": 0.015005350112915039}, "transfer_0.8": {"AUC ROC": 1.0, "AUC PR": 1.0, "CLL": -0.063719, "Precision": [1.0, 0.5], "Recall": 1.0, "F1": 1.0, "Learning time": 6.567517763137817, "parameter": {"AUC ROC": 0.5, "AUC PR": 0.021267, "CLL": -0.390737, "Precision": [NaN, 0.5], "Recall": 0.0, "F1": NaN}, "Mapping time": 0.015005350112915039}, "transfer_1.0": {"AUC ROC": 1.0, "AUC PR": 1.0, "CLL": -0.063719, "Precision": [1.0, 0.5], "Recall": 1.0, "F1": 1.0, "Learning time": 7.5112611618042, "parameter": {"AUC ROC": 0.5, "AUC PR": 0.021267, "CLL": -0.382698, "Precision": [NaN, 0.5], "Recall": 0.0, "F1": NaN}, "Mapping time": 0.015005350112915039}}]]