[[{"transfer_0.2": {"AUC ROC": 0.781276, "AUC PR": 0.129374, "CLL": -0.312382, "Precision": [0.212766, 0.5], "Recall": 0.192308, "F1": 0.20202, "Learning time": 31.38988452339172, "parameter": {"AUC ROC": 0.511312, "AUC PR": 0.001469, "CLL": -0.366647, "Precision": [NaN, 0.5], "Recall": 0.0, "F1": NaN, "Learning time": 1.652}, "Mapping time": 5.667269468307495}, "transfer_0.4": {"AUC ROC": 0.643923, "AUC PR": 0.081125, "CLL": -0.327831, "Precision": [0.290323, 0.5], "Recall": 0.103846, "F1": 0.152975, "Learning time": 40.24756892776489, "parameter": {"AUC ROC": 0.519331, "AUC PR": 0.001495, "CLL": -0.369527, "Precision": [NaN, 0.5], "Recall": 0.0, "F1": NaN, "Learning time": 2.222}, "Mapping time": 5.667269468307495}, "transfer_0.6": {"AUC ROC": 0.741329, "AUC PR": 0.093743, "CLL": -0.325103, "Precision": [0.355556, 0.5], "Recall": 0.123077, "F1": 0.182857, "Learning time": 83.48504117393493, "parameter": {"AUC ROC": 0.507293, "AUC PR": 0.001435, "CLL": -0.37157, "Precision": [NaN, 0.5], "Recall": 0.0, "F1": NaN, "Learning time": 3.08}, "Mapping time": 5.667269468307495}, "transfer_0.8": {"AUC ROC": 0.740052, "AUC PR": 0.126235, "CLL": -0.323974, "Precision": [0.528571, 0.5], "Recall": 0.142308, "F1": 0.224242, "Learning time": 80.50774538230897, "parameter": {"AUC ROC": 0.509091, "AUC PR": 0.001446, "CLL": -0.364108, "Precision": [NaN, 0.5], "Recall": 0.0, "F1": NaN, "Learning time": 3.671}, "Mapping time": 5.667269468307495}, "transfer_1.0": {"AUC ROC": 0.585121, "AUC PR": 0.052503, "CLL": -0.352644, "Precision": [0.423729, 0.5], "Recall": 0.096154, "F1": 0.15674, "Learning time": 82.39387712669372, "parameter": {"AUC ROC": 0.503987, "AUC PR": 0.001421, "CLL": -0.367559, "Precision": [NaN, 0.5], "Recall": 0.0, "F1": NaN, "Learning time": 4.49}, "Mapping time": 5.667269468307495}}, {"transfer_0.2": {"AUC ROC": 0.701551, "AUC PR": 0.038116, "CLL": -0.330178, "Precision": [0.148148, 0.5], "Recall": 0.092308, "F1": 0.113744, "Learning time": 34.42773065757751, "parameter": {"AUC ROC": 0.503324, "AUC PR": 0.001397, "CLL": -0.375845, "Precision": [NaN, 0.5], "Recall": 0.0, "F1": NaN, "Learning time": 1.69}, "Mapping time": 5.667269468307495}, "transfer_0.4": {"AUC ROC": 0.653319, "AUC PR": 0.066813, "CLL": -0.353712, "Precision": [0.349206, 0.5], "Recall": 0.084615, "F1": 0.136223, "Learning time": 42.443957593917844, "parameter": {"AUC ROC": 0.516555, "AUC PR": 0.001444, "CLL": -0.36924, "Precision": [NaN, 0.5], "Recall": 0.0, "F1": NaN, "Learning time": 2.347}, "Mapping time": 5.667269468307495}, "transfer_0.6": {"AUC ROC": 0.696059, "AUC PR": 0.066347, "CLL": -0.330706, "Precision": [0.182353, 0.5], "Recall": 0.119231, "F1": 0.144186, "Learning time": 66.21217207336426, "parameter": {"AUC ROC": 0.489403, "AUC PR": 0.001314, "CLL": -0.372125, "Precision": [NaN, 0.5], "Recall": 0.0, "F1": NaN, "Learning time": 2.945}, "Mapping time": 5.667269468307495}, "transfer_0.8": {"AUC ROC": 0.67134, "AUC PR": 0.080106, "CLL": -0.328579, "Precision": [0.352113, 0.5], "Recall": 0.096154, "F1": 0.151057, "Learning time": 72.94874657440185, "parameter": {"AUC ROC": 0.489187, "AUC PR": 0.001317, "CLL": -0.370108, "Precision": [NaN, 0.5], "Recall": 0.0, "F1": NaN, "Learning time": 3.665}, "Mapping time": 5.667269468307495}, "transfer_1.0": {"AUC ROC": 0.582691, "AUC PR": 0.031248, "CLL": -0.346363, "Precision": [0.352113, 0.5], "Recall": 0.096154, "F1": 0.151057, "Learning time": 85.98319640350343, "parameter": {"AUC ROC": 0.488904, "AUC PR": 0.001313, "CLL": -0.369507, "Precision": [NaN, 0.5], "Recall": 0.0, "F1": NaN, "Learning time": 4.337}, "Mapping time": 5.667269468307495}}, {"transfer_0.2": {"AUC ROC": 0.702007, "AUC PR": 0.0836, "CLL": -0.349857, "Precision": [0.230159, 0.5], "Recall": 0.112403, "F1": 0.151042, "Learning time": 26.540816621780394, "parameter": {"AUC ROC": 0.501882, "AUC PR": 0.001381, "CLL": -0.372298, "Precision": [NaN, 0.5], "Recall": 0.0, "F1": NaN, "Learning time": 1.718}, "Mapping time": 5.667269468307495}, "transfer_0.4": {"AUC ROC": 0.724518, "AUC PR": 0.063656, "CLL": -0.327088, "Precision": [0.076087, 0.5], "Recall": 0.244186, "F1": 0.116022, "Learning time": 47.99886541557312, "parameter": {"AUC ROC": 0.506553, "AUC PR": 0.001426, "CLL": -0.367085, "Precision": [NaN, 0.5], "Recall": 0.0, "F1": NaN, "Learning time": 2.468}, "Mapping time": 5.667269468307495}, "transfer_0.6": {"AUC ROC": 0.632556, "AUC PR": 0.052688, "CLL": -0.343161, "Precision": [0.360465, 0.5], "Recall": 0.120155, "F1": 0.180233, "Learning time": 81.10532340240479, "parameter": {"AUC ROC": 0.495878, "AUC PR": 0.001354, "CLL": -0.365628, "Precision": [NaN, 0.5], "Recall": 0.0, "F1": NaN, "Learning time": 3.044}, "Mapping time": 5.667269468307495}, "transfer_0.8": {"AUC ROC": 0.744916, "AUC PR": 0.08283, "CLL": -0.326272, "Precision": [0.395349, 0.5], "Recall": 0.131783, "F1": 0.197674, "Learning time": 88.67446438789368, "parameter": {"AUC ROC": 0.495878, "AUC PR": 0.001354, "CLL": -0.366349, "Precision": [NaN, 0.5], "Recall": 0.0, "F1": NaN, "Learning time": 3.65}, "Mapping time": 5.667269468307495}, "transfer_1.0": {"AUC ROC": 0.763259, "AUC PR": 0.098487, "CLL": -0.329461, "Precision": [0.391753, 0.5], "Recall": 0.147287, "F1": 0.214085, "Learning time": 101.37176708030701, "parameter": {"AUC ROC": 0.494907, "AUC PR": 0.001346, "CLL": -0.371435, "Precision": [NaN, 0.5], "Recall": 0.0, "F1": NaN, "Learning time": 4.332}, "Mapping time": 5.667269468307495}}], [{"transfer_0.2": {"AUC ROC": 0.71322, "AUC PR": 0.03712, "CLL": -0.309621, "Precision": [0.069079, 0.5], "Recall": 0.242308, "F1": 0.107509, "Learning time": 39.93454634094238, "parameter": {"AUC ROC": 0.505656, "AUC PR": 0.001433, "CLL": -0.373434, "Precision": [NaN, 0.5], "Recall": 0.0, "F1": NaN, "Learning time": 1.82}, "Mapping time": 5.663116693496704}, "transfer_0.4": {"AUC ROC": 0.786152, "AUC PR": 0.124688, "CLL": -0.324668, "Precision": [0.25, 0.5], "Recall": 0.157692, "F1": 0.193396, "Learning time": 49.46949633979797, "parameter": {"AUC ROC": 0.510578, "AUC PR": 0.001467, "CLL": -0.351319, "Precision": [NaN, 0.5], "Recall": 0.0, "F1": NaN, "Learning time": 2.358}, "Mapping time": 5.663116693496704}, "transfer_0.6": {"AUC ROC": 0.595412, "AUC PR": 0.054274, "CLL": -0.344805, "Precision": [0.466667, 0.5], "Recall": 0.107692, "F1": 0.175, "Learning time": 56.1445775642395, "parameter": {"AUC ROC": 0.510684, "AUC PR": 0.001452, "CLL": -0.368969, "Precision": [NaN, 0.5], "Recall": 0.0, "F1": NaN, "Learning time": 2.985}, "Mapping time": 5.663116693496704}, "transfer_0.8": {"AUC ROC": 0.774174, "AUC PR": 0.12677, "CLL": -0.321572, "Precision": [0.333333, 0.5], "Recall": 0.134615, "F1": 0.191781, "Learning time": 85.45571226882934, "parameter": {"AUC ROC": 0.510684, "AUC PR": 0.001452, "CLL": -0.373963, "Precision": [NaN, 0.5], "Recall": 0.0, "F1": NaN, "Learning time": 3.768}, "Mapping time": 5.663116693496704}, "transfer_1.0": {"AUC ROC": 0.723419, "AUC PR": 0.117285, "CLL": -0.32869, "Precision": [0.523077, 0.5], "Recall": 0.130769, "F1": 0.209231, "Learning time": 101.63752513504028, "parameter": {"AUC ROC": 0.503968, "AUC PR": 0.00142, "CLL": -0.367959, "Precision": [NaN, 0.5], "Recall": 0.0, "F1": NaN, "Learning time": 4.674}, "Mapping time": 5.663116693496704}}, {"transfer_0.2": {"AUC ROC": 0.665238, "AUC PR": 0.038745, "CLL": -0.32903, "Precision": [0.185841, 0.5], "Recall": 0.080769, "F1": 0.112601, "Learning time": 27.27193498039246, "parameter": {"AUC ROC": 0.505375, "AUC PR": 0.001403, "CLL": -0.365038, "Precision": [0.000825, 0.5], "Recall": 0.011538, "F1": 0.00154, "Learning time": 1.653}, "Mapping time": 5.663116693496704}, "transfer_0.4": {"AUC ROC": 0.582728, "AUC PR": 0.050069, "CLL": -0.336528, "Precision": [0.527778, 0.5], "Recall": 0.073077, "F1": 0.128378, "Learning time": 40.04433143615722, "parameter": {"AUC ROC": 0.505091, "AUC PR": 0.001397, "CLL": -0.374599, "Precision": [NaN, 0.5], "Recall": 0.0, "F1": NaN, "Learning time": 2.353}, "Mapping time": 5.663116693496704}, "transfer_0.6": {"AUC ROC": 0.631907, "AUC PR": 0.067855, "CLL": -0.329843, "Precision": [0.282609, 0.5], "Recall": 0.1, "F1": 0.147727, "Learning time": 62.15770616149902, "parameter": {"AUC ROC": 0.493272, "AUC PR": 0.001333, "CLL": -0.369189, "Precision": [NaN, 0.5], "Recall": 0.0, "F1": NaN, "Learning time": 3.1}, "Mapping time": 5.663116693496704}, "transfer_0.8": {"AUC ROC": 0.714024, "AUC PR": 0.066187, "CLL": -0.331596, "Precision": [0.131387, 0.5], "Recall": 0.138462, "F1": 0.134831, "Learning time": 131.8519290790558, "parameter": {"AUC ROC": 0.503862, "AUC PR": 0.001372, "CLL": -0.371552, "Precision": [NaN, 0.5], "Recall": 0.0, "F1": NaN, "Learning time": 3.704}, "Mapping time": 5.663116693496704}, "transfer_1.0": {"AUC ROC": 0.72207, "AUC PR": 0.078295, "CLL": -0.31098, "Precision": [0.082171, 0.5], "Recall": 0.203846, "F1": 0.117127, "Learning time": 104.16372721290588, "parameter": {"AUC ROC": 0.488837, "AUC PR": 0.001313, "CLL": -0.372032, "Precision": [NaN, 0.5], "Recall": 0.0, "F1": NaN, "Learning time": 4.49}, "Mapping time": 5.663116693496704}}, {"transfer_0.2": {"AUC ROC": 0.754278, "AUC PR": 0.049506, "CLL": -0.325568, "Precision": [0.045249, 0.5], "Recall": 0.310078, "F1": 0.078973, "Learning time": 38.08601521682739, "parameter": {"AUC ROC": 0.51877, "AUC PR": 0.001453, "CLL": -0.364174, "Precision": [NaN, 0.5], "Recall": 0.0, "F1": NaN, "Learning time": 1.768}, "Mapping time": 5.663116693496704}, "transfer_0.4": {"AUC ROC": 0.7324, "AUC PR": 0.115182, "CLL": -0.334828, "Precision": [0.576923, 0.5], "Recall": 0.05814, "F1": 0.105634, "Learning time": 48.928570600509644, "parameter": {"AUC ROC": 0.503943, "AUC PR": 0.001384, "CLL": -0.36871, "Precision": [NaN, 0.5], "Recall": 0.0, "F1": NaN, "Learning time": 2.394}, "Mapping time": 5.663116693496704}, "transfer_0.6": {"AUC ROC": 0.724155, "AUC PR": 0.079975, "CLL": -0.331078, "Precision": [0.088274, 0.5], "Recall": 0.25969, "F1": 0.13176, "Learning time": 89.55622304344178, "parameter": {"AUC ROC": 0.502294, "AUC PR": 0.001381, "CLL": -0.36979, "Precision": [NaN, 0.5], "Recall": 0.0, "F1": NaN, "Learning time": 2.946}, "Mapping time": 5.663116693496704}, "transfer_0.8": {"AUC ROC": 0.570807, "AUC PR": 0.044854, "CLL": -0.359733, "Precision": [0.416667, 0.5], "Recall": 0.03876, "F1": 0.070922, "Learning time": 65.84171502113342, "parameter": {"AUC ROC": 0.490799, "AUC PR": 0.001333, "CLL": -0.371086, "Precision": [NaN, 0.5], "Recall": 0.0, "F1": NaN, "Learning time": 3.668}, "Mapping time": 5.663116693496704}, "transfer_1.0": {"AUC ROC": 0.717066, "AUC PR": 0.076339, "CLL": -0.330604, "Precision": [0.441176, 0.5], "Recall": 0.116279, "F1": 0.184049, "Learning time": 104.22649143218993, "parameter": {"AUC ROC": 0.490228, "AUC PR": 0.001338, "CLL": -0.372571, "Precision": [NaN, 0.5], "Recall": 0.0, "F1": NaN, "Learning time": 4.404}, "Mapping time": 5.663116693496704}}], [{"transfer_0.2": {"AUC ROC": 0.687317, "AUC PR": 0.062122, "CLL": -0.34513, "Precision": [0.040221, 0.5], "Recall": 0.196154, "F1": 0.066754, "Learning time": 35.949906501770016, "parameter": {"AUC ROC": 0.505775, "AUC PR": 0.001433, "CLL": -0.377483, "Precision": [NaN, 0.5], "Recall": 0.0, "F1": NaN, "Learning time": 1.791}, "Mapping time": 5.663207292556763}, "transfer_0.4": {"AUC ROC": 0.759041, "AUC PR": 0.090268, "CLL": -0.329305, "Precision": [0.117444, 0.5], "Recall": 0.261538, "F1": 0.162098, "Learning time": 77.32207524108887, "parameter": {"AUC ROC": 0.50612, "AUC PR": 0.001433, "CLL": -0.374102, "Precision": [NaN, 0.5], "Recall": 0.0, "F1": NaN, "Learning time": 2.417}, "Mapping time": 5.663207292556763}, "transfer_0.6": {"AUC ROC": 0.766233, "AUC PR": 0.12459, "CLL": -0.327851, "Precision": [0.460317, 0.5], "Recall": 0.111538, "F1": 0.179567, "Learning time": 113.22377939033508, "parameter": {"AUC ROC": 0.509072, "AUC PR": 0.001444, "CLL": -0.367681, "Precision": [NaN, 0.5], "Recall": 0.0, "F1": NaN, "Learning time": 3.111}, "Mapping time": 5.663207292556763}, "transfer_0.8": {"AUC ROC": 0.751148, "AUC PR": 0.118014, "CLL": -0.328443, "Precision": [0.452055, 0.5], "Recall": 0.126923, "F1": 0.198198, "Learning time": 143.35165048217772, "parameter": {"AUC ROC": 0.514222, "AUC PR": 0.001475, "CLL": -0.362936, "Precision": [NaN, 0.5], "Recall": 0.0, "F1": NaN, "Learning time": 3.783}, "Mapping time": 5.663207292556763}, "transfer_1.0": {"AUC ROC": 0.77334, "AUC PR": 0.138606, "CLL": -0.325003, "Precision": [0.506849, 0.5], "Recall": 0.142308, "F1": 0.222222, "Learning time": 87.59828694152831, "parameter": {"AUC ROC": 0.50612, "AUC PR": 0.001433, "CLL": -0.364299, "Precision": [NaN, 0.5], "Recall": 0.0, "F1": NaN, "Learning time": 4.153}, "Mapping time": 5.663207292556763}}, {"transfer_0.2": {"AUC ROC": 0.735338, "AUC PR": 0.059175, "CLL": -0.311017, "Precision": [0.052166, 0.5], "Recall": 0.226923, "F1": 0.084831, "Learning time": 34.885643810272214, "parameter": {"AUC ROC": 0.493272, "AUC PR": 0.001333, "CLL": -0.363267, "Precision": [NaN, 0.5], "Recall": 0.0, "F1": NaN, "Learning time": 1.653}, "Mapping time": 5.663207292556763}, "transfer_0.4": {"AUC ROC": 0.711363, "AUC PR": 0.058866, "CLL": -0.312799, "Precision": [0.067275, 0.5], "Recall": 0.226923, "F1": 0.103782, "Learning time": 72.60854640769958, "parameter": {"AUC ROC": 0.499684, "AUC PR": 0.001355, "CLL": -0.366631, "Precision": [NaN, 0.5], "Recall": 0.0, "F1": NaN, "Learning time": 2.411}, "Mapping time": 5.663207292556763}, "transfer_0.6": {"AUC ROC": 0.696989, "AUC PR": 0.061138, "CLL": -0.331256, "Precision": [0.2, 0.5], "Recall": 0.076923, "F1": 0.111111, "Learning time": 75.65225511932373, "parameter": {"AUC ROC": 0.505454, "AUC PR": 0.001404, "CLL": -0.363118, "Precision": [NaN, 0.5], "Recall": 0.0, "F1": NaN, "Learning time": 3.002}, "Mapping time": 5.663207292556763}, "transfer_0.8": {"AUC ROC": 0.695272, "AUC PR": 0.069312, "CLL": -0.310793, "Precision": [0.092257, 0.5], "Recall": 0.215385, "F1": 0.129181, "Learning time": 76.98475803947449, "parameter": {"AUC ROC": 0.491024, "AUC PR": 0.001321, "CLL": -0.373247, "Precision": [NaN, 0.5], "Recall": 0.0, "F1": NaN, "Learning time": 3.7}, "Mapping time": 5.663207292556763}, "transfer_1.0": {"AUC ROC": 0.597463, "AUC PR": 0.074254, "CLL": -0.341019, "Precision": [0.35443, 0.5], "Recall": 0.107692, "F1": 0.165192, "Learning time": 85.67197139167786, "parameter": {"AUC ROC": 0.489187, "AUC PR": 0.001317, "CLL": -0.368961, "Precision": [NaN, 0.5], "Recall": 0.0, "F1": NaN, "Learning time": 4.36}, "Mapping time": 5.663207292556763}}, {"transfer_0.2": {"AUC ROC": 0.740204, "AUC PR": 0.045712, "CLL": -0.311851, "Precision": [0.05425, 0.5], "Recall": 0.116279, "F1": 0.073983, "Learning time": 41.8539407863617, "parameter": {"AUC ROC": 0.495807, "AUC PR": 0.00135, "CLL": -0.355206, "Precision": [NaN, 0.5], "Recall": 0.0, "F1": NaN, "Learning time": 1.62}, "Mapping time": 5.663207292556763}, "transfer_0.4": {"AUC ROC": 0.726273, "AUC PR": 0.098103, "CLL": -0.325999, "Precision": [0.472222, 0.5], "Recall": 0.131783, "F1": 0.206061, "Learning time": 41.05255584526062, "parameter": {"AUC ROC": 0.491771, "AUC PR": 0.001346, "CLL": -0.365064, "Precision": [NaN, 0.5], "Recall": 0.0, "F1": NaN, "Learning time": 2.409}, "Mapping time": 5.663207292556763}, "transfer_0.6": {"AUC ROC": 0.732879, "AUC PR": 0.104842, "CLL": -0.335073, "Precision": [0.492063, 0.5], "Recall": 0.120155, "F1": 0.193146, "Learning time": 64.67029963874816, "parameter": {"AUC ROC": 0.497931, "AUC PR": 0.001364, "CLL": -0.374169, "Precision": [NaN, 0.5], "Recall": 0.0, "F1": NaN, "Learning time": 3.036}, "Mapping time": 5.663207292556763}, "transfer_0.8": {"AUC ROC": 0.715734, "AUC PR": 0.0533, "CLL": -0.313181, "Precision": [0.074975, 0.5], "Recall": 0.286822, "F1": 0.118876, "Learning time": 113.25838117027283, "parameter": {"AUC ROC": 0.497078, "AUC PR": 0.001369, "CLL": -0.361544, "Precision": [NaN, 0.5], "Recall": 0.0, "F1": NaN, "Learning time": 3.694}, "Mapping time": 5.663207292556763}, "transfer_1.0": {"AUC ROC": 0.781475, "AUC PR": 0.127633, "CLL": -0.326797, "Precision": [0.39604, 0.5], "Recall": 0.155039, "F1": 0.222841, "Learning time": 222.50805340385438, "parameter": {"AUC ROC": 0.491033, "AUC PR": 0.001339, "CLL": -0.368449, "Precision": [NaN, 0.5], "Recall": 0.0, "F1": NaN, "Learning time": 4.304}, "Mapping time": 5.663207292556763}}]]